Workbook

Sheet S&P500 Valuation
C2: Valuation of S&P 500 | E2: =IF(OR(C5="",C6="",C7="",C9="",C8=""),"Provide Correct Input",SUM(E13:E23)) -> 2608.315 | I2: Total Yield | J2: EPS Growth | K2: RFR | L2: ERP
B3: Key inputs | D3: Assumptions | E3: =IF(OR(C5="",C6="",C7="",C9="",C8=""),"Provide Correct Input",IF(E2>1.02*C5,"Undervalued",IF(E2<0.98*D5,"Overvalued","Fairly Valued"))) -> Overvalued | I3: 20 Years | J3: 3 Years | K3: 20 Years | L3: 20 Years
B4: Date | C4: =TODAY() -> 45540 | D4: =TODAY() -> 45540 | E4: =IF(OR(C5="",C6="",C7="",C9="",C8=""),"Provide Correct Input","The Market implied fair value of S&P 500 index is" & ROUNDUP(E2,0)&". The current market value of the S&P 500 index is" &ROUNDUP(D5,0)&". A "&TEXT(ABS((E2-C5)/C5),"0.00%")& " "&IF(E3="Overvalued","Appreciation",IF(E3="Undervalued","Correction","Adjustment")&"Expected from this level.")) -> The Market implied fair value of S&P 500 index is2609. The current market value of the S&P 500 index is5598. A 53.40% Appreciation | I4: 15 Years | J4: 5 Years | K4: 15 Years | L4: 15 Years
B5: Current S&P 500 Levels | C5: 5597.12 | D5: 5597.12 | I5: 10 Years | J5: 7 Years | K5: 7 Years | L5: 7 Years
B6: Total Yield | C6: 10 Years | D6: =VLOOKUP(C6,'ExpectedDiv&BB'!J3:L13,2,0) -> 0.042355429 | I6: 7 Years | J6: 10 Years | K6: 5 Years | L6: 5 Years
B7: Expected Growth | C7: 10 Years | D7: =VLOOKUP(C7,'S&P500growthEPS'!Y4:Z10,2,0) -> 0.065979145 | I7: 5 Years | K7: Latest | L7: Latest
B8: Risk Free Rate | C8: Latest | D8: =VLOOKUP(C8,'10 yr Govt Bond yield'!M2:N10,2,0) -> 0.039670833 | I8: 3 Years
B9: Equity Risk Premium | C9: Latest | D9: =VLOOKUP(C9,ERPHistoricals!G3:H11,2,0) -> 0.046
B10: Cost of Equity | D10: =D9+D8 -> 0.085670833
C11: Expected Dividends | D11: Cumulative PV Factor (Risk-Free | E11: Present Value of Expected Dividends and
B12: Year | C12: and Buybacks | D12: Rate + Equity Risk Premium) | E12: Buybacks
B13: 2023 | C13: =$D$5*$D$6+(1+$D$7)^(B13-($B$13-1)) -> 238.1344 | D13: =1/((1+$D$10)^(B13-($B$13-1))) -> 0.9210895 | E13: =C13*D13 -> 219.34309
B14: =B13+1 -> 2024 | C14: =$D$5*$D$6+(1+$D$7)^(B14-($B$13-1)) -> 238.20473 | D14: =1/((1+$D$10)^(B14-($B$13-1))) -> 0.84840586 | E14: =C14*D14 -> 202.09429
B15: =B14+1 -> 2025 | C15: =$D$5*$D$6+(1+$D$7)^(B15-($B$13-1)) -> 238.2797 | D15: =1/((1+$D$10)^(B15-($B$13-1))) -> 0.78145772 | E15: =C15*D15 -> 186.20551
B16: =B15+1 -> 2026 | C16: =$D$5*$D$6+(1+$D$7)^(B16-($B$13-1)) -> 238.35962 | D16: =1/((1+$D$10)^(B16-($B$13-1))) -> 0.7197925 | E16: =C16*D16 -> 171.56947
B17: =B16+1 -> 2027 | C17: =$D$5*$D$6+(1+$D$7)^(B17-($B$13-1)) -> 238.44481 | D17: =1/((1+$D$10)^(B17-($B$13-1))) -> 0.66299331 | E17: =C17*D17 -> 158.08732
B18: =B17+1 -> 2028 | C18: =$D$5*$D$6+(1+$D$7)^(B18-($B$13-1)) -> 238.53563 | D18: =1/((1+$D$10)^(B18-($B$13-1))) -> 0.61067617 | E18: =C18*D18 -> 145.66802
B19: =B18+1 -> 2029 | C19: =$D$5*$D$6+(1+$D$7)^(B19-($B$13-1)) -> 238.63243 | D19: =1/((1+$D$10)^(B19-($B$13-1))) -> 0.56248741 | E19: =C19*D19 -> 134.22774
B20: =B19+1 -> 2030 | C20: =$D$5*$D$6+(1+$D$7)^(B20-($B$13-1)) -> 238.73563 | D20: =1/((1+$D$10)^(B20-($B$13-1))) -> 0.51810124 | E20: =C20*D20 -> 123.68922
B21: =B20+1 -> 2031 | C21: =$D$5*$D$6+(1+$D$7)^(B21-($B$13-1)) -> 238.84563 | D21: =1/((1+$D$10)^(B21-($B$13-1))) -> 0.47721761 | E21: =C21*D21 -> 113.98134
B22: =B21+1 -> 2032 | C22: =$D$5*$D$6+(1+$D$7)^(B22-($B$13-1)) -> 238.96288 | D22: =1/((1+$D$10)^(B22-($B$13-1))) -> 0.43956013 | E22: =C22*D22 -> 105.03856
B23: Terminal Year | C23: =SUM(C13:C22) -> 2385.1355 | D23: =D22 -> 0.43956013 | E23: =C23*D23 -> 1048.4105

Sheet S&P500growthEPS
B1: Year | C1: Earnings Yield | D1: Dividend Yield | E1: S&P 500 | F1: Earnings | G1: Dividends | H1: Payout Ratio
B2: 1960 | C2: 0.0534 | D2: 0.0341 | E2: 58.11 | F2: 3.1 | G2: 1.98 | H2: 0.6386
B3: 1961 | C3: 0.0471 | D3: 0.0285 | E3: 71.55 | F3: 3.37 | G3: 2.04 | H3: 0.6051
B4: 1962 | C4: 0.0581 | D4: 0.034 | E4: 63.1 | F4: 3.67 | G4: 2.15 | H4: 0.5852 | X4: Average CAGR S&P500 Return- | Y4: 3 Years | Z4: =AVERAGE(S15:S65) -> 0.082081686
B5: 1963 | C5: 0.0551 | D5: 0.0313 | E5: 75.02 | F5: 4.13 | G5: 2.35 | H5: 0.5681
B6: 1964 | C6: 0.0562 | D6: 0.0305 | E6: 84.75 | F6: 4.76 | G6: 2.58 | H6: 0.5427 | X6: Average CAGR S&P500 Return- | Y6: 5 Years | Z6: =AVERAGE(T17:T65) -> 0.073393255
B7: 1965 | C7: 0.0573 | D7: 0.0306 | E7: 92.43 | F7: 5.3 | G7: 2.83 | H7: 0.534
B8: 1966 | C8: 0.0674 | D8: 0.0359 | E8: 80.33 | F8: 5.41 | G8: 2.88 | H8: 0.5326 | X8: Average CAGR S&P500 Return- | Y8: 7 Years | Z8: =AVERAGE(U19:U65) -> 0.067634594
B9: 1967 | C9: 0.0566 | D9: 0.0309 | E9: 96.47 | F9: 5.46 | G9: 2.98 | H9: 0.5459
B10: 1968 | C10: 0.0551 | D10: 0.0293 | E10: 103.86 | F10: 5.72 | G10: 3.04 | H10: 0.5318 | X10: Average CAGR S&P500 Return- | Y10: 10 Years | Z10: =AVERAGE(V22:V65) -> 0.065979145
B11: 1969 | C11: 0.0663 | D11: 0.0352 | E11: 92.06 | F11: 6.1 | G11: 3.24 | H11: 0.5309 | N11: Year | O11: P/E Ratio | P11: S&P Average Range | R11: EPS | S11: EPS CAGR 3 Years | T11: EPS CAGR 5Years | U11: EPS CAGR 7Years | V11: EPS CAGR 10 Years
B12: 1970 | C12: 0.0598 | D12: 0.0346 | E12: 92.15 | F12: 5.51 | G12: 3.19 | H12: 0.5786 | N12: 1970 | O12: 15.76 | P12: 83.281818 | R12: =P12/O12 -> 5.2843793
B13: 1971 | C13: 0.0546 | D13: 0.031 | E13: 102.09 | F13: 5.57 | G13: 3.16 | H13: 0.5678 | N13: 1971 | O13: 18.12 | P13: 98.291667 | R13: =P13/O13 -> 5.4244849
B14: 1972 | C14: 0.0523 | D14: 0.027 | E14: 118.05 | F14: 6.17 | G14: 3.19 | H14: 0.5163 | N14: 1972 | O14: 18.01 | P14: 109.775 | R14: =P14/O14 -> 6.0952249
B15: 1973 | C15: 0.0816 | D15: 0.037 | E15: 97.55 | F15: 7.96 | G15: 3.61 | H15: 0.4534 | N15: 1973 | O15: 18.09 | P15: 106.50833 | R15: =P15/O15 -> 5.8876912 | S15: =_xlfn.RRI(3,R12,R15) -> 0.036693429
B16: 1974 | C16: 0.1364 | D16: 0.0543 | E16: 68.56 | F16: 9.35 | G16: 3.72 | H16: 0.3981 | N16: 1974 | O16: 11.68 | P16: 81.491667 | R16: =P16/O16 -> 6.9770263 | S16: =_xlfn.RRI(3,R13,R16) -> 0.087520078
B17: 1975 | C17: 0.0855 | D17: 0.0414 | E17: 90.19 | F17: 7.71 | G17: 3.73 | H17: 0.4842 | N17: 1975 | O17: 8.3 | P17: 87.141667 | R17: =P17/O17 -> 10.498996 | S17: =_xlfn.RRI(3,R14,R17) -> 0.1987244 | T17: =_xlfn.RRI(5,R12,R17) -> 0.14717786
B18: 1976 | C18: 0.0907 | D18: 0.0393 | E18: 107.46 | F18: 9.75 | G18: 4.22 | H18: 0.4333 | N18: 1976 | O18: 11.82 | P18: 102.79167 | R18: =P18/O18 -> 8.6964185 | S18: =_xlfn.RRI(3,R15,R18) -> 0.13884636 | T18: =_xlfn.RRI(5,R13,R18) -> 0.098996692
B19: 1977 | C19: 0.1143 | D19: 0.0511 | E19: 95.1 | F19: 10.87 | G19: 4.86 | H19: 0.4471 | N19: 1977 | O19: 10.41 | P19: 97.458333 | R19: =P19/O19 -> 9.3619917 | S19: =_xlfn.RRI(3,R16,R19) -> 0.10297575 | T19: =_xlfn.RRI(5,R14,R19) -> 0.089621599 | U19: =_xlfn.RRI(7,R12,R19) -> 0.085130669
B20: 1978 | C20: 0.1211 | D20: 0.0539 | E20: 96.11 | F20: 11.64 | G20: 5.18 | H20: 0.4451 | N20: 1978 | O20: 8.28 | P20: 95.45 | R20: =P20/O20 -> 11.527778 | S20: =_xlfn.RRI(3,R17,R20) -> 0.031650537 | T20: =_xlfn.RRI(5,R15,R20) -> 0.1438264 | U20: =_xlfn.RRI(7,R13,R20) -> 0.1137035
B21: 1979 | C21: 0.1348 | D21: 0.0553 | E21: 107.94 | F21: 14.55 | G21: 5.97 | H21: 0.4102 | N21: 1979 | O21: 7.88 | P21: 103.325 | R21: =P21/O21 -> 13.11231 | S21: =_xlfn.RRI(3,R18,R21) -> 0.14669061 | T21: =_xlfn.RRI(5,R16,R21) -> 0.13449286 | U21: =_xlfn.RRI(7,R14,R21) -> 0.11564768
B22: 1980 | C22: 0.1104 | D22: 0.0474 | E22: 135.76 | F22: 14.99 | G22: 6.44 | H22: 0.4293 | N22: 1980 | O22: 7.39 | P22: 119.59167 | R22: =P22/O22 -> 16.182905 | S22: =_xlfn.RRI(3,R19,R22) -> 0.20013309 | T22: =_xlfn.RRI(5,R17,R22) -> 0.090389704 | U22: =_xlfn.RRI(7,R15,R22) -> 0.15539427 | V22: =_xlfn.RRI(10,R12,R22) -> 0.11842341
B23: 1981 | C23: 0.1239 | D23: 0.0557 | E23: 122.55 | F23: 15.18 | G23: 6.83 | H23: 0.4496 | N23: 1981 | O23: 9.02 | P23: 127.85 | R23: =P23/O23 -> 14.174058 | S23: =_xlfn.RRI(3,R20,R23) -> 0.071312568 | T23: =_xlfn.RRI(5,R18,R23) -> 0.10263241 | U23: =_xlfn.RRI(7,R16,R23) -> 0.10655966 | V23: =_xlfn.RRI(10,R13,R23) -> 0.10081305
B24: 1982 | C24: 0.0983 | D24: 0.0493 | E24: 140.64 | F24: 13.82 | G24: 6.93 | H24: 0.5015 | N24: 1982 | O24: 7.73 | P24: 120.26667 | R24: =P24/O24 -> 15.55843 | S24: =_xlfn.RRI(3,R21,R24) -> 0.058673871 | T24: =_xlfn.RRI(5,R19,R24) -> 0.10692834 | U24: =_xlfn.RRI(7,R17,R24) -> 0.057797589 | V24: =_xlfn.RRI(10,R14,R24) -> 0.098240878
B25: 1983 | C25: 0.0806 | D25: 0.0432 | E25: 164.93 | F25: 13.29 | G25: 7.12 | H25: 0.536 | N25: 1983 | O25: 11.48 | P25: 160.775 | R25: =P25/O25 -> 14.004791 | S25: =_xlfn.RRI(3,R22,R25) -> -0.047042827 | T25: =_xlfn.RRI(5,R20,R25) -> 0.039695602 | U25: =_xlfn.RRI(7,R18,R25) -> 0.070439962 | V25: =_xlfn.RRI(10,R15,R25) -> 0.09051881
B26: 1984 | C26: 0.1007 | D26: 0.0468 | E26: 167.24 | F26: 16.84 | G26: 7.83 | H26: 0.4647 | N26: 1984 | O26: 11.52 | P26: 160.33333 | R26: =P26/O26 -> 13.917824 | S26: =_xlfn.RRI(3,R23,R26) -> -0.0060625619 | T26: =_xlfn.RRI(5,R21,R26) -> 0.011995146 | U26: =_xlfn.RRI(7,R19,R26) -> 0.058279642 | V26: =_xlfn.RRI(10,R16,R26) -> 0.071494876
B27: 1985 | C27: 0.0742 | D27: 0.0388 | E27: 211.28 | F27: 15.68 | G27: 8.2 | H27: 0.5229 | N27: 1985 | O27: 10.36 | P27: 188.96667 | R27: =P27/O27 -> 18.240026 | S27: =_xlfn.RRI(3,R24,R27) -> 0.054435184 | T27: =_xlfn.RRI(5,R22,R27) -> 0.024221277 | U27: =_xlfn.RRI(7,R20,R27) -> 0.067747468 | V27: =_xlfn.RRI(10,R17,R27) -> 0.056787743
B28: 1986 | C28: 0.0596 | D28: 0.0338 | E28: 242.17 | F28: 14.43 | G28: 8.19 | H28: 0.5671 | N28: 1986 | O28: 14.28 | P28: 238.90833 | R28: =P28/O28 -> 16.730275 | S28: =_xlfn.RRI(3,R25,R28) -> 0.061065402 | T28: =_xlfn.RRI(5,R23,R28) -> 0.033717287 | U28: =_xlfn.RRI(7,R21,R28) -> 0.035422741 | V28: =_xlfn.RRI(10,R18,R28) -> 0.067618931
B29: 1987 | C29: 0.0649 | D29: 0.0371 | E29: 247.08 | F29: 16.04 | G29: 9.17 | H29: 0.5716 | N29: 1987 | O29: 18.01 | P29: 286 | R29: =P29/O29 -> 15.880067 | S29: =_xlfn.RRI(3,R26,R29) -> 0.044945546 | T29: =_xlfn.RRI(5,R24,R29) -> 0.0041007883 | U29: =_xlfn.RRI(7,R22,R29) -> -0.0026950441 | V29: =_xlfn.RRI(10,R19,R29) -> 0.054261645
B30: 1988 | C30: 0.0869 | D30: 0.0368 | E30: 277.72 | F30: 24.12 | G30: 9.75 | H30: 0.4042 | N30: 1988 | O30: 14.02 | P30: 268.05 | R30: =P30/O30 -> 19.119116 | S30: =_xlfn.RRI(3,R27,R30) -> 0.01581382 | T30: =_xlfn.RRI(5,R25,R30) -> 0.064236705 | U30: =_xlfn.RRI(7,R23,R30) -> 0.043680712 | V30: =_xlfn.RRI(10,R20,R30) -> 0.051894587
B31: 1989 | C31: 0.0688 | D31: 0.0332 | E31: 353.4 | F31: 24.32 | G31: 11.06 | H31: 0.4548 | N31: 1989 | O31: 11.82 | P31: 326.31667 | R31: =P31/O31 -> 27.607163 | S31: =_xlfn.RRI(3,R28,R31) -> 0.18169726 | T31: =_xlfn.RRI(5,R26,R31) -> 0.14680635 | U31: =_xlfn.RRI(7,R24,R31) -> 0.085374036 | V31: =_xlfn.RRI(10,R21,R31) -> 0.077294043
B32: 1990 | C32: 0.0686 | D32: 0.0374 | E32: 330.22 | F32: 22.65 | G32: 12.09 | H32: 0.5338 | N32: 1990 | O32: 15.13 | P32: 332.675 | R32: =P32/O32 -> 21.987773 | S32: =_xlfn.RRI(3,R29,R32) -> 0.11457588 | T32: =_xlfn.RRI(5,R27,R32) -> 0.038080799 | U32: =_xlfn.RRI(7,R25,R32) -> 0.066562654 | V32: =_xlfn.RRI(10,R22,R32) -> 0.031127752
B33: 1991 | C33: 0.0463 | D33: 0.0311 | E33: 417.09 | F33: 19.3 | G33: 12.2 | H33: 0.6321 | N33: 1991 | O33: 15.35 | P33: 381.54167 | R33: =P33/O33 -> 24.856135 | S33: =_xlfn.RRI(3,R30,R33) -> 0.091411683 | T33: =_xlfn.RRI(5,R28,R33) -> 0.082395805 | U33: =_xlfn.RRI(7,R26,R33) -> 0.086376397 | V33: =_xlfn.RRI(10,R23,R33) -> 0.057776562
... B65: 2023 | C65: 0.0461 | D65: 0.0147 | E65: 4769.83 | F65: 219.7 | G65: 70.3 | H65: 0.32 | N65: 2023 | O65: 22.82 | P65: 4322.6542 | R65: =P65/O65 -> 189.42393 | S65: =_xlfn.RRI(3,R62,R65) -> 0.13574313 | T65: =_xlfn.RRI(5,R60,R65) -> 0.11550477 | U65: =_xlfn.RRI(7,R58,R65) -> 0.10370586 | V65: =_xlfn.RRI(10,R55,R65) -> 0.069193423

Sheet ExpectedDiv&BB
B2: Year | C2: S&P Average Range | D2: Dividend Yield | E2: Dividend Amount | F2: BB Amount | G2: Total Yield
B3: 1970 | C3: 83.281818 | D3: 0.0346 | E3: =C3*D3 -> 2.8815509 | F3: =E3*'Buyback Yield'!$L$6 -> 3.9482938 | G3: =(E3+F3)/C3 -> 0.082008832 | I3: Average Return- | J3: 20 Years | K3: =AVERAGE(G37:G56) -> 0.045069305
B4: 1971 | C4: 98.291667 | D4: 0.031 | E4: =C4*D4 -> 3.0470417 | F4: =E4*'Buyback Yield'!$L$6 -> 4.1750488 | G4: =(E4+F4)/C4 -> 0.073476122
B5: 1972 | C5: 109.775 | D5: 0.027 | E5: =C5*D5 -> 2.963925 | F5: =E5*'Buyback Yield'!$L$6 -> 4.0611625 | G5: =(E5+F5)/C5 -> 0.063995332 | I5: Average Return- | J5: 15 Years | K5: =AVERAGE(G42:G56) -> 0.043975064
B6: 1973 | C6: 106.50833 | D6: 0.037 | E6: =C6*D6 -> 3.9408083 | F6: =E6*'Buyback Yield'!$L$6 -> 5.3996856 | G6: =(E6+F6)/C6 -> 0.087697306
B7: 1974 | C7: 81.491667 | D7: 0.0543 | E7: =C7*D7 -> 4.4249975 | F7: =E7*'Buyback Yield'!$L$6 -> 6.0631204 | G7: =(E7+F7)/C7 -> 0.12870172 | I7: Average Return- | J7: 10 Years | K7: =AVERAGE(G47:G56) -> 0.042355429
B8: 1975 | C8: 87.141667 | D8: 0.0414 | E8: =C8*D8 -> 3.607665 | F8: =E8*'Buyback Yield'!$L$6 -> 4.9432135 | G8: =(E8+F8)/C8 -> 0.098126175
B9: 1976 | C9: 102.79167 | D9: 0.0393 | E9: =C9*D9 -> 4.0397125 | F9: =E9*'Buyback Yield'!$L$6 -> 5.5352039 | G9: =(E9+F9)/C9 -> 0.093148761 | I9: Average Return- | J9: 7 Years | K9: =AVERAGE(G50:G56) -> 0.039920897
B10: 1977 | C10: 97.458333 | D10: 0.0511 | E10: =C10*D10 -> 4.9801208 | F10: =E10*'Buyback Yield'!$L$6 -> 6.823749 | G10: =(E10+F10)/C10 -> 0.12111709
B11: 1978 | C11: 95.45 | D11: 0.0539 | E11: =C11*D11 -> 5.144755 | F11: =E11*'Buyback Yield'!$L$6 -> 7.0493303 | G11: =(E11+F11)/C11 -> 0.12775364 | I11: Average Return- | J11: 5 Years | K11: =AVERAGE(G52:G56) -> 0.037069888
B12: 1979 | C12: 103.325 | D12: 0.0553 | E12: =C12*D12 -> 5.7138725 | F12: =E12*'Buyback Yield'!$L$6 -> 7.8291336 | G12: =(E12+F12)/C12 -> 0.13107192
B13: 1980 | C13: 119.59167 | D13: 0.0474 | E13: =C13*D13 -> 5.668645 | F13: =E13*'Buyback Yield'!$L$6 -> 7.767163 | G13: =(E13+F13)/C13 -> 0.11234736 | I13: Average Return- | J13: 3 Years | K13: =AVERAGE(G54:G56) -> 0.035473955
B14: 1981 | C14: 127.85 | D14: 0.0557 | E14: =C14*D14 -> 7.121245 | F14: =E14*'Buyback Yield'!$L$6 -> 9.7575119 | G14: =(E14+F14)/C14 -> 0.13202
B15: 1982 | C15: 120.26667 | D15: 0.0493 | E15: =C15*D15 -> 5.9291467 | F15: =E15*'Buyback Yield'!$L$6 -> 8.1241018 | G15: =(E15+F15)/C15 -> 0.11685074
B16: 1983 | C16: 160.775 | D16: 0.0432 | E16: =C16*D16 -> 6.94548 | F16: =E16*'Buyback Yield'!$L$6 -> 9.5166791 | G16: =(E16+F16)/C16 -> 0.10239253
B17: 1984 | C17: 160.33333 | D17: 0.0468 | E17: =C17*D17 -> 7.5036 | F17: =E17*'Buyback Yield'!$L$6 -> 10.281414 | G17: =(E17+F17)/C17 -> 0.11092524
B18: 1985 | C18: 188.96667 | D18: 0.0388 | E18: =C18*D18 -> 7.3319067 | F18: =E18*'Buyback Yield'!$L$6 -> 10.04616 | G18: =(E18+F18)/C18 -> 0.091963662
B19: 1986 | C19: 238.90833 | D19: 0.0338 | E19: =C19*D19 -> 8.0751017 | F19: =E19*'Buyback Yield'!$L$6 -> 11.064484 | G19: =(E19+F19)/C19 -> 0.080112675
B20: 1987 | C20: 286 | D20: 0.0371 | E20: =C20*D20 -> 10.6106 | F20: =E20*'Buyback Yield'!$L$6 -> 14.538617 | G20: =(E20+F20)/C20 -> 0.087934326
B21: 1988 | C21: 268.05 | D21: 0.0368 | E21: =C21*D21 -> 9.86424 | F21: =E21*'Buyback Yield'!$L$6 -> 13.515957 | G21: =(E21+F21)/C21 -> 0.087223267
B22: 1989 | C22: 326.31667 | D22: 0.0332 | E22: =C22*D22 -> 10.833713 | F22: =E22*'Buyback Yield'!$L$6 -> 14.844327 | G22: =(E22+F22)/C22 -> 0.078690556
B23: 1990 | C23: 332.675 | D23: 0.0374 | E23: =C23*D23 -> 12.442045 | F23: =E23*'Buyback Yield'!$L$6 -> 17.048059 | G23: =(E23+F23)/C23 -> 0.088645385
B24: 1991 | C24: 381.54167 | D24: 0.0311 | E24: =C24*D24 -> 11.865946 | F24: =E24*'Buyback Yield'!$L$6 -> 16.258689 | G24: =(E24+F24)/C24 -> 0.073713141
B25: 1992 | C25: 417.11667 | D25: 0.029 | E25: =C25*D25 -> 12.096383 | F25: =E25*'Buyback Yield'!$L$6 -> 16.574434 | G25: =(E25+F25)/C25 -> 0.068735727
... B56: 2023 | C56: 4322.6542 | D56: 0.0147 | E56: =C56*D56 -> 63.543016 | F56: =E56*'Buyback Yield'!$L$6 -> 87.06648 | G56: =(E56+F56)/C56 -> 0.034841903

Sheet S&P500 Historical
B2: Date | C2: Price | D2: Open | E2: High | F2: Low | G2: Vol. | H2: Change % | I2: Monthly Returns | L2: Year | M2: S&P Average Range | N2: Average Return
B3: 25600 | C3: 89.5 | D3: 89.5 | E3: 89.5 | F3: 89.5 | H3: 0.0529 | L3: 1970 | M3: =AVERAGEIFS($C$3:$C$649,$B$3:$B$649,">="&DATE(L3,1,1),$B$3:$B$649,"<="&DATE(L3,12,1)) -> 83.281818
B4: 25628 | C4: 89.6 | D4: 89.6 | E4: 89.6 | F4: 89.6 | H4: 0.0011 | I4: =F4/F3-1 -> 0.0011173184 | L4: =L3+1 -> 1971 | M4: =AVERAGEIFS($C$3:$C$649,$B$3:$B$649,">="&DATE(L4,1,1),$B$3:$B$649,"<="&DATE(L4,12,1)) -> 98.291667 | N4: =M4/M3-1 -> 0.1802296 | P4: CAGR S&P500 Return- | Q4: 20 Years | R4: =_xlfn.RRI(20,M37,M56) -> 0.069197241
B5: 25659 | C5: 81.5 | D5: 81.5 | E5: 81.5 | F5: 81.5 | H5: -0.0904 | I5: =F5/F4-1 -> -0.090401786 | L5: =L4+1 -> 1972 | M5: =AVERAGEIFS($C$3:$C$649,$B$3:$B$649,">="&DATE(L5,1,1),$B$3:$B$649,"<="&DATE(L5,12,1)) -> 109.775 | N5: =M5/M4-1 -> 0.11682916
B6: 25689 | C6: 76.5 | D6: 76.5 | E6: 76.5 | F6: 76.5 | H6: -0.0613 | I6: =F6/F5-1 -> -0.061349693 | L6: =L5+1 -> 1973 | M6: =AVERAGEIFS($C$3:$C$649,$B$3:$B$649,">="&DATE(L6,1,1),$B$3:$B$649,"<="&DATE(L6,12,1)) -> 106.50833 | N6: =M6/M5-1 -> -0.029757838 | P6: CAGR S&P500 Return- | Q6: 15 Years | R6: =_xlfn.RRI(15,M42,M56) -> 0.10640391
B7: 25720 | C7: 72.7 | D7: 72.7 | E7: 72.7 | F7: 72.7 | H7: -0.0497 | I7: =F7/F6-1 -> -0.049673203 | L7: =L6+1 -> 1974 | M7: =AVERAGEIFS($C$3:$C$649,$B$3:$B$649,">="&DATE(L7,1,1),$B$3:$B$649,"<="&DATE(L7,12,1)) -> 81.491667 | N7: =M7/M6-1 -> -0.2348799
B8: 25750 | C8: 78 | D8: 78 | E8: 78 | F8: 78 | H8: 0.0729 | I8: =F8/F7-1 -> 0.072902338 | L8: =L7+1 -> 1975 | M8: =AVERAGEIFS($C$3:$C$649,$B$3:$B$649,">="&DATE(L8,1,1),$B$3:$B$649,"<="&DATE(L8,12,1)) -> 87.141667 | N8: =M8/M7-1 -> 0.069332243 | P8: CAGR S&P500 Return- | Q8: 10 Years | R8: =_xlfn.RRI(10,M47,M56) -> 0.083168827
B9: 25781 | C9: 81.5 | D9: 81.5 | E9: 81.5 | F9: 81.5 | H9: 0.0449 | I9: =F9/F8-1 -> 0.044871795 | L9: =L8+1 -> 1976 | M9: =AVERAGEIFS($C$3:$C$649,$B$3:$B$649,">="&DATE(L9,1,1),$B$3:$B$649,"<="&DATE(L9,12,1)) -> 102.79167 | N9: =M9/M8-1 -> 0.17959262
B10: 25812 | C10: 84.2 | D10: 84.2 | E10: 84.2 | F10: 84.2 | H10: 0.0331 | I10: =F10/F9-1 -> 0.033128834 | L10: =L9+1 -> 1977 | M10: =AVERAGEIFS($C$3:$C$649,$B$3:$B$649,">="&DATE(L10,1,1),$B$3:$B$649,"<="&DATE(L10,12,1)) -> 97.458333 | N10: =M10/M9-1 -> -0.05188488 | P10: CAGR S&P500 Return- | Q10: 7 Years | R10: =_xlfn.RRI(7,M50,M56) -> 0.083534188
B11: 25842 | C11: 83.2 | D11: 83.2 | E11: 83.2 | F11: 83.2 | H11: -0.0119 | I11: =F11/F10-1 -> -0.011876485 | L11: =L10+1 -> 1978 | M11: =AVERAGEIFS($C$3:$C$649,$B$3:$B$649,">="&DATE(L11,1,1),$B$3:$B$649,"<="&DATE(L11,12,1)) -> 95.45 | N11: =M11/M10-1 -> -0.020607097
B12: 25873 | C12: 87.2 | D12: 87.2 | E12: 87.2 | F12: 87.2 | H12: 0.0481 | I12: =F12/F11-1 -> 0.048076923 | L12: =L11+1 -> 1979 | M12: =AVERAGEIFS($C$3:$C$649,$B$3:$B$649,">="&DATE(L12,1,1),$B$3:$B$649,"<="&DATE(L12,12,1)) -> 103.325 | N12: =M12/M11-1 -> 0.082503929 | P12: CAGR S&P500 Return- | Q12: 5 Years | R12: =_xlfn.RRI(5,M52,M56) -> 0.080291287
B13: 25903 | C13: 92.2 | D13: 92.2 | E13: 92.2 | F13: 92.2 | H13: 0.0573 | I13: =F13/F12-1 -> 0.05733945 | L13: =L12+1 -> 1980 | M13: =AVERAGEIFS($C$3:$C$649,$B$3:$B$649,">="&DATE(L13,1,1),$B$3:$B$649,"<="&DATE(L13,12,1)) -> 119.59167 | N13: =M13/M12-1 -> 0.15743205
B14: 25934 | C14: 95.9 | D14: 95.9 | E14: 95.9 | F14: 95.9 | H14: 0.0401 | I14: =F14/F13-1 -> 0.040130152 | L14: =L13+1 -> 1981 | M14: =AVERAGEIFS($C$3:$C$649,$B$3:$B$649,">="&DATE(L14,1,1),$B$3:$B$649,"<="&DATE(L14,12,1)) -> 127.85 | N14: =M14/M13-1 -> 0.069054421
B15: 25965 | C15: 96.8 | D15: 96.8 | E15: 96.8 | F15: 96.8 | H15: 0.0094 | I15: =F15/F14-1 -> 0.0093847758 | L15: =L14+1 -> 1982 | M15: =AVERAGEIFS($C$3:$C$649,$B$3:$B$649,">="&DATE(L15,1,1),$B$3:$B$649,"<="&DATE(L15,12,1)) -> 120.26667 | N15: =M15/M14-1 -> -0.059314301
B16: 25993 | C16: 100.3 | D16: 100.3 | E16: 100.3 | F16: 100.3 | H16: 0.0362 | I16: =F16/F15-1 -> 0.036157025 | L16: =L15+1 -> 1983 | M16: =AVERAGEIFS($C$3:$C$649,$B$3:$B$649,">="&DATE(L16,1,1),$B$3:$B$649,"<="&DATE(L16,12,1)) -> 160.775 | N16: =M16/M15-1 -> 0.33682095
B17: 26024 | C17: 104 | D17: 104 | E17: 104 | F17: 104 | H17: 0.0369 | I17: =F17/F16-1 -> 0.036889332 | L17: =L16+1 -> 1984 | M17: =AVERAGEIFS($C$3:$C$649,$B$3:$B$649,">="&DATE(L17,1,1),$B$3:$B$649,"<="&DATE(L17,12,1)) -> 160.33333 | N17: =M17/M16-1 -> -0.0027471104
B18: 26054 | C18: 99.6 | D18: 99.6 | E18: 99.6 | F18: 99.6 | H18: -0.0423 | I18: =F18/F17-1 -> -0.042307692 | L18: =L17+1 -> 1985 | M18: =AVERAGEIFS($C$3:$C$649,$B$3:$B$649,">="&DATE(L18,1,1),$B$3:$B$649,"<="&DATE(L18,12,1)) -> 188.96667 | N18: =M18/M17-1 -> 0.17858628
B19: 26085 | C19: 99.7 | D19: 99.7 | E19: 99.7 | F19: 99.7 | H19: 0.001 | I19: =F19/F18-1 -> 0.0010040161 | L19: =L18+1 -> 1986 | M19: =AVERAGEIFS($C$3:$C$649,$B$3:$B$649,">="&DATE(L19,1,1),$B$3:$B$649,"<="&DATE(L19,12,1)) -> 238.90833 | N19: =M19/M18-1 -> 0.26428823
B20: 26115 | C20: 95.6 | D20: 95.6 | E20: 95.6 | F20: 95.6 | H20: -0.0411 | I20: =F20/F19-1 -> -0.04112337 | L20: =L19+1 -> 1987 | M20: =AVERAGEIFS($C$3:$C$649,$B$3:$B$649,">="&DATE(L20,1,1),$B$3:$B$649,"<="&DATE(L20,12,1)) -> 286 | N20: =M20/M19-1 -> 0.19711186
B21: 26146 | C21: 99 | D21: 99 | E21: 99 | F21: 99 | H21: 0.0356 | I21: =F21/F20-1 -> 0.035564854 | L21: =L20+1 -> 1988 | M21: =AVERAGEIFS($C$3:$C$649,$B$3:$B$649,">="&DATE(L21,1,1),$B$3:$B$649,"<="&DATE(L21,12,1)) -> 268.05 | N21: =M21/M20-1 -> -0.062762238
B22: 26177 | C22: 98.3 | D22: 98.3 | E22: 98.3 | F22: 98.3 | H22: -0.0071 | I22: =F22/F21-1 -> -0.0070707071 | L22: =L21+1 -> 1989 | M22: =AVERAGEIFS($C$3:$C$649,$B$3:$B$649,">="&DATE(L22,1,1),$B$3:$B$649,"<="&DATE(L22,12,1)) -> 326.31667 | N22: =M22/M21-1 -> 0.21737238
B23: 26207 | C23: 94.2 | D23: 94.2 | E23: 94.2 | F23: 94.2 | H23: -0.0417 | I23: =F23/F22-1 -> -0.041709054 | L23: =L22+1 -> 1990 | M23: =AVERAGEIFS($C$3:$C$649,$B$3:$B$649,">="&DATE(L23,1,1),$B$3:$B$649,"<="&DATE(L23,12,1)) -> 332.675 | N23: =M23/M22-1 -> 0.019485163
B24: 26238 | C24: 94 | D24: 94 | E24: 94 | F24: 94 | H24: -0.0021 | I24: =F24/F23-1 -> -0.0021231423 | L24: =L23+1 -> 1991 | M24: =AVERAGEIFS($C$3:$C$649,$B$3:$B$649,">="&DATE(L24,1,1),$B$3:$B$649,"<="&DATE(L24,12,1)) -> 381.54167 | N24: =M24/M23-1 -> 0.14689011
... B56: 27211 | C56: 79.3 | D56: 79.3 | E56: 79.3 | F56: 79.3 | H56: -0.0779 | I56: =F56/F55-1 -> -0.077906977 | L56: =L55+1 -> 2023 | M56: =AVERAGEIFS($C$3:$C$649,$B$3:$B$649,">="&DATE(L56,1,1),$B$3:$B$649,"<="&DATE(L56,12,1)) -> 4322.6542 | N56: =M56/M55-1 -> 0.060083349
B57: 27242 | C57: 72.2 | D57: 72.2 | E57: 72.2 | F57: 72.2 | H57: -0.0895 | I57: =F57/F56-1 -> -0.089533417
B58: 27273 | C58: 63.5 | D58: 63.5 | E58: 63.5 | F58: 63.5 | H58: -0.1205 | I58: =F58/F57-1 -> -0.12049861
B59: 27303 | C59: 73.9 | D59: 73.9 | E59: 73.9 | F59: 73.9 | H59: 0.1638 | I59: =F59/F58-1 -> 0.16377953
B60: 27334 | C60: 70 | D60: 70 | E60: 70 | F60: 70 | H60: -0.0528 | I60: =F60/F59-1 -> -0.052774019
B61: 27364 | C61: 68.6 | D61: 68.6 | E61: 68.6 | F61: 68.6 | H61: -0.02 | I61: =F61/F60-1 -> -0.02
B62: 27395 | C62: 77 | D62: 77 | E62: 78.7 | F62: 68.7 | H62: 0.1224 | I62: =F62/F61-1 -> 0.0014577259
B63: 27426 | C63: 81.6 | D63: 81.6 | E63: 83.6 | F63: 76 | H63: 0.0597 | I63: =F63/F62-1 -> 0.1062591
B64: 27454 | C64: 83.4 | D64: 83.4 | E64: 87.1 | F64: 80.1 | H64: 0.0221 | I64: =F64/F63-1 -> 0.053947368
B65: 27485 | C65: 87.3 | D65: 87.3 | E65: 88.8 | F65: 79.7 | H65: 0.0468 | I65: =F65/F64-1 -> -0.0049937578
B66: 27515 | C66: 91.2 | D66: 91.2 | E66: 93.5 | F66: 86.9 | H66: 0.0447 | I66: =F66/F65-1 -> 0.09033877
B67: 27546 | C67: 95.2 | D67: 95.2 | E67: 95.8 | F67: 89.3 | H67: 0.0439 | I67: =F67/F66-1 -> 0.027617952
B68: 27576 | C68: 88.8 | D68: 88.8 | E68: 96.6 | F68: 87.7 | H68: -0.0672 | I68: =F68/F67-1 -> -0.017917133
... B649: 45261 | C649: 4769.83 | D649: 4559.43 | E649: 4793.3 | F649: 4546.5 | H649: 0.0442 | I649: =F649/F648-1 -> 0.083082802

Sheet 10 yr Govt Bond yield
B2: Date | C2: Price | D2: Open | E2: High | F2: Low | G2: Change % | I2: Year | J2: 10Y Bond Average | L2: Average Rate- | M2: 20 Years | N2: =AVERAGE(J37:J56) -> 0.028819458
B3: 25600 | C3: 0.0724 | D3: 0.0724 | E3: 0.0724 | F3: 0.0724 | G3: -0.0706 | I3: 1970 | J3: =AVERAGEIFS($C$3:$C$649,$B$3:$B$649,">="&DATE(I3,1,1),$B$3:$B$649,"<="&DATE(I3,12,1)) -> 0.073081818
B4: 25628 | C4: 0.0707 | D4: 0.0707 | E4: 0.0707 | F4: 0.0707 | G4: -0.0235 | I4: =I3+1 -> 1971 | J4: =AVERAGEIFS($C$3:$C$649,$B$3:$B$649,">="&DATE(I4,1,1),$B$3:$B$649,"<="&DATE(I4,12,1)) -> 0.061591667 | L4: Average Rate- | M4: 15 Years | N4: =AVERAGE(J42:J56) -> 0.024112333
B5: 25659 | C5: 0.0739 | D5: 0.0739 | E5: 0.0739 | F5: 0.0739 | G5: 0.0453 | I5: =I4+1 -> 1972 | J5: =AVERAGEIFS($C$3:$C$649,$B$3:$B$649,">="&DATE(I5,1,1),$B$3:$B$649,"<="&DATE(I5,12,1)) -> 0.0621
B6: 25689 | C6: 0.0791 | D6: 0.0791 | E6: 0.0791 | F6: 0.0791 | G6: 0.0704 | I6: =I5+1 -> 1973 | J6: =AVERAGEIFS($C$3:$C$649,$B$3:$B$649,">="&DATE(I6,1,1),$B$3:$B$649,"<="&DATE(I6,12,1)) -> 0.068425 | L6: Average Rate- | M6: 7 Years | N6: =AVERAGE(J50:J56) -> 0.023637262
B7: 25720 | C7: 0.0784 | D7: 0.0784 | E7: 0.0784 | F7: 0.0784 | G7: -0.0088 | I7: =I6+1 -> 1974 | J7: =AVERAGEIFS($C$3:$C$649,$B$3:$B$649,">="&DATE(I7,1,1),$B$3:$B$649,"<="&DATE(I7,12,1)) -> 0.075575
B8: 25750 | C8: 0.0746 | D8: 0.0746 | E8: 0.0746 | F8: 0.0746 | G8: -0.0485 | I8: =I7+1 -> 1975 | J8: =AVERAGEIFS($C$3:$C$649,$B$3:$B$649,">="&DATE(I8,1,1),$B$3:$B$649,"<="&DATE(I8,12,1)) -> 0.079875 | L8: Average Rate- | M8: 5 Years | N8: =AVERAGE(J52:J56) -> 0.02264
B9: 25781 | C9: 0.0753 | D9: 0.0753 | E9: 0.0753 | F9: 0.0753 | G9: 0.0094 | I9: =I8+1 -> 1976 | J9: =AVERAGEIFS($C$3:$C$649,$B$3:$B$649,">="&DATE(I9,1,1),$B$3:$B$649,"<="&DATE(I9,12,1)) -> 0.076116667
B10: 25812 | C10: 0.0739 | D10: 0.0739 | E10: 0.0739 | F10: 0.0739 | G10: -0.0186 | I10: =I9+1 -> 1977 | J10: =AVERAGEIFS($C$3:$C$649,$B$3:$B$649,">="&DATE(I10,1,1),$B$3:$B$649,"<="&DATE(I10,12,1)) -> 0.074191667 | L10: Average Rate- | M10: Latest | N10: =J56 -> 0.039670833
B11: 25842 | C11: 0.0733 | D11: 0.0733 | E11: 0.0733 | F11: 0.0733 | G11: -0.0081 | I11: =I10+1 -> 1978 | J11: =AVERAGEIFS($C$3:$C$649,$B$3:$B$649,">="&DATE(I11,1,1),$B$3:$B$649,"<="&DATE(I11,12,1)) -> 0.0841
B12: 25873 | C12: 0.0684 | D12: 0.0684 | E12: 0.0684 | F12: 0.0684 | G12: -0.0668 | I12: =I11+1 -> 1979 | J12: =AVERAGEIFS($C$3:$C$649,$B$3:$B$649,">="&DATE(I12,1,1),$B$3:$B$649,"<="&DATE(I12,12,1)) -> 0.094425
B13: 25903 | C13: 0.0639 | D13: 0.0639 | E13: 0.0639 | F13: 0.0639 | G13: -0.0658 | I13: =I12+1 -> 1980 | J13: =AVERAGEIFS($C$3:$C$649,$B$3:$B$649,">="&DATE(I13,1,1),$B$3:$B$649,"<="&DATE(I13,12,1)) -> 0.11413583
B14: 25934 | C14: 0.0624 | D14: 0.0624 | E14: 0.0624 | F14: 0.0624 | G14: -0.0235 | I14: =I13+1 -> 1981 | J14: =AVERAGEIFS($C$3:$C$649,$B$3:$B$649,">="&DATE(I14,1,1),$B$3:$B$649,"<="&DATE(I14,12,1)) -> 0.14012917
B15: 25965 | C15: 0.0611 | D15: 0.0611 | E15: 0.0611 | F15: 0.0611 | G15: -0.0208 | I15: =I14+1 -> 1982 | J15: =AVERAGEIFS($C$3:$C$649,$B$3:$B$649,">="&DATE(I15,1,1),$B$3:$B$649,"<="&DATE(I15,12,1)) -> 0.1294825
B16: 25993 | C16: 0.057 | D16: 0.057 | E16: 0.057 | F16: 0.057 | G16: -0.0671 | I16: =I15+1 -> 1983 | J16: =AVERAGEIFS($C$3:$C$649,$B$3:$B$649,">="&DATE(I16,1,1),$B$3:$B$649,"<="&DATE(I16,12,1)) -> 0.11136917
B17: 26024 | C17: 0.0583 | D17: 0.0583 | E17: 0.0583 | F17: 0.0583 | G17: 0.0228 | I17: =I16+1 -> 1984 | J17: =AVERAGEIFS($C$3:$C$649,$B$3:$B$649,">="&DATE(I17,1,1),$B$3:$B$649,"<="&DATE(I17,12,1)) -> 0.12481333
B18: 26054 | C18: 0.0639 | D18: 0.0639 | E18: 0.0639 | F18: 0.0639 | G18: 0.0961 | I18: =I17+1 -> 1985 | J18: =AVERAGEIFS($C$3:$C$649,$B$3:$B$649,">="&DATE(I18,1,1),$B$3:$B$649,"<="&DATE(I18,12,1)) -> 0.10533583
B19: 26085 | C19: 0.0652 | D19: 0.0652 | E19: 0.0652 | F19: 0.0652 | G19: 0.0203 | I19: =I18+1 -> 1986 | J19: =AVERAGEIFS($C$3:$C$649,$B$3:$B$649,">="&DATE(I19,1,1),$B$3:$B$649,"<="&DATE(I19,12,1)) -> 0.0756325
B20: 26115 | C20: 0.0673 | D20: 0.0673 | E20: 0.0673 | F20: 0.0673 | G20: 0.0322 | I20: =I19+1 -> 1987 | J20: =AVERAGEIFS($C$3:$C$649,$B$3:$B$649,">="&DATE(I20,1,1),$B$3:$B$649,"<="&DATE(I20,12,1)) -> 0.0839725
B21: 26146 | C21: 0.0658 | D21: 0.0658 | E21: 0.0658 | F21: 0.0658 | G21: -0.0223 | I21: =I20+1 -> 1988 | J21: =AVERAGEIFS($C$3:$C$649,$B$3:$B$649,">="&DATE(I21,1,1),$B$3:$B$649,"<="&DATE(I21,12,1)) -> 0.088300833
B22: 26177 | C22: 0.0614 | D22: 0.0614 | E22: 0.0614 | F22: 0.0614 | G22: -0.0669 | I22: =I21+1 -> 1989 | J22: =AVERAGEIFS($C$3:$C$649,$B$3:$B$649,">="&DATE(I22,1,1),$B$3:$B$649,"<="&DATE(I22,12,1)) -> 0.084510833
... B56: 27211 | C56: 0.0781 | D56: 0.0781 | E56: 0.0781 | F56: 0.0781 | G56: 0.0358 | I56: =I55+1 -> 2023 | J56: =AVERAGEIFS($C$3:$C$649,$B$3:$B$649,">="&DATE(I56,1,1),$B$3:$B$649,"<="&DATE(I56,12,1)) -> 0.039670833
B57: 27242 | C57: 0.0804 | D57: 0.0804 | E57: 0.0804 | F57: 0.0804 | G57: 0.0294
B58: 27273 | C58: 0.0804 | D58: 0.0804 | E58: 0.0804 | F58: 0.0804 | G58: 0
B59: 27303 | C59: 0.079 | D59: 0.079 | E59: 0.079 | F59: 0.079 | G59: -0.0174
B60: 27334 | C60: 0.0768 | D60: 0.0768 | E60: 0.0768 | F60: 0.0768 | G60: -0.0278
B61: 27364 | C61: 0.0743 | D61: 0.0743 | E61: 0.0743 | F61: 0.0743 | G61: -0.0326
B62: 27395 | C62: 0.075 | D62: 0.075 | E62: 0.075 | F62: 0.075 | G62: 0.0094
B63: 27426 | C63: 0.0739 | D63: 0.0739 | E63: 0.0739 | F63: 0.0739 | G63: -0.0147
B64: 27454 | C64: 0.0773 | D64: 0.0773 | E64: 0.0773 | F64: 0.0773 | G64: 0.046
B65: 27485 | C65: 0.0823 | D65: 0.0823 | E65: 0.0823 | F65: 0.0823 | G65: 0.0647
B66: 27515 | C66: 0.0806 | D66: 0.0806 | E66: 0.0806 | F66: 0.0806 | G66: -0.0207
B67: 27546 | C67: 0.0786 | D67: 0.0786 | E67: 0.0786 | F67: 0.0786 | G67: -0.0248
B68: 27576 | C68: 0.0806 | D68: 0.0806 | E68: 0.0806 | F68: 0.0806 | G68: 0.0254
... B649: 45261 | C649: 0.03866 | D649: 0.04321 | E649: 0.04349 | F649: 0.03783 | G649: -0.1072

Sheet ERPHistoricals
B2: Year | C2: Implied ERP (FCFE)
B3: 1970 | C3: 0.0341 | F3: Average Implied ERP- | G3: 20 Years | H3: =AVERAGE(C37:C56) -> 0.051165
B4: 1971 | C4: 0.0309
B5: 1972 | C5: 0.0272 | F5: Average Implied ERP- | G5: 15 Years | H5: =AVERAGE(C42:C56) -> 0.053093333
B6: 1973 | C6: 0.043
B7: 1974 | C7: 0.0559 | F7: Average Implied ERP- | G7: 7 Years | H7: =AVERAGE(C50:C56) -> 0.051057143
B8: 1975 | C8: 0.0413
B9: 1976 | C9: 0.0455 | F9: Average Implied ERP- | G9: 5 Years | H9: =AVERAGE(C52:C56) -> 0.0494
B10: 1977 | C10: 0.0592
B11: 1978 | C11: 0.0572 | F11: Average Implied ERP- | G11: Latest | H11: =C56 -> 0.046
B12: 1979 | C12: 0.0645
B13: 1980 | C13: 0.0503
B14: 1981 | C14: 0.0573
B15: 1982 | C15: 0.049
B16: 1983 | C16: 0.0431
B17: 1984 | C17: 0.0511
B18: 1985 | C18: 0.0384
B19: 1986 | C19: 0.0358
B20: 1987 | C20: 0.0399
B21: 1988 | C21: 0.0377
B22: 1989 | C22: 0.0351
B23: 1990 | C23: 0.0389
... B56: 2023 | C56: 0.046
B57: Source: | C57: Aswath Damodaran

Sheet Buyback Yield
B2: Industry name | C2: Number of firms | D2: Dividends | E2: Net Income | F2: Payout | G2: Dividends + Buybacks | H2: buyback | I2: buyback%dividend
B3: Advertising | C3: 57 | D3: 1059.36 | E3: 374.54 | F3: 282.84 | G3: =3012 -> 3012 | H3: 19.5264
B4: Aerospace/Defense | C4: 70 | D4: 10325.45 | E4: 19229.93 | F4: 53.69 | G4: 25778.4 | H4: =IF(D4>G4,0,G4-D4) -> 15452.95 | I4: =IFERROR(H4/D4,0) -> 1.4965885 | K4: Mean | L4: =AVERAGE(H4:H98) -> 25741.398
B5: Air Transport | C5: 25 | D5: 503.1 | E5: 6398.1 | F5: 7.86 | G5: 986.34 | H5: =IF(D5>G5,0,G5-D5) -> 483.24 | I5: =IFERROR(H5/D5,0) -> 0.96052475 | K5: Mean | L5: =AVERAGE(I4:I96) -> 218.40362
B6: Apparel | C6: 38 | D6: 1691.36 | E6: 2255.65 | F6: 74.98 | G6: 3578.14 | H6: =IF(D6>G6,0,G6-D6) -> 1886.78 | I6: =IFERROR(H6/D6,0) -> 1.1155402 | K6: Trimmed Mean | L6: =TRIMMEAN(I4:I98,0.3) -> 1.3701975
B7: Auto & Truck | C7: 34 | D7: 5839.1 | E7: 16467.08 | F7: 35.46 | G7: 8873.28 | H7: =IF(D7>G7,0,G7-D7) -> 3034.18 | I7: =IFERROR(H7/D7,0) -> 0.51963145
B8: Auto Parts | C8: 39 | D8: 705.75 | E8: 1555.7 | F8: 45.37 | G8: 1237.74 | H8: =IF(D8>G8,0,G8-D8) -> 531.99 | I8: =IFERROR(H8/D8,0) -> 0.75379384
B9: Bank (Money Center) | C9: 15 | D9: 34903.05 | E9: 143409.88 | F9: 24.34 | G9: 36941 | H9: =IF(D9>G9,0,G9-D9) -> 2037.95 | I9: =IFERROR(H9/D9,0) -> 0.05838888
B10: Banks (Regional) | C10: 625 | D10: 18260.63 | E10: 57038.42 | F10: 32.01 | G10: 23938.6 | H10: =IF(D10>G10,0,G10-D10) -> 5677.97 | I10: =IFERROR(H10/D10,0) -> 0.31094053
B11: Beverage (Alcoholic) | C11: 19 | D11: 1374.5 | E11: 2515.8 | F11: 54.63 | G11: 1909.32 | H11: =IF(D11>G11,0,G11-D11) -> 534.82 | I11: =IFERROR(H11/D11,0) -> 0.38910149
B12: Beverage (Soft) | C12: 29 | D12: 15531.3 | E12: 23394.15 | F12: 66.39 | G12: 19583.24 | H12: =IF(D12>G12,0,G12-D12) -> 4051.94 | I12: =IFERROR(H12/D12,0) -> 0.26088866
B13: Broadcasting | C13: 22 | D13: 1166.89 | E13: -1028.55 | F13: 0.22 | G13: 4534.39 | H13: =IF(D13>G13,0,G13-D13) -> 3367.5 | I13: =IFERROR(H13/D13,0) -> 2.8858761
B14: Brokerage & Investment Banking | C14: 27 | D14: 12346.39 | E14: 28366.14 | F14: 43.53 | G14: 26575.42 | H14: =IF(D14>G14,0,G14-D14) -> 14229.03 | I14: =IFERROR(H14/D14,0) -> 1.1524851
B15: Building Materials | C15: 44 | D15: 3011.12 | E15: 10376.23 | F15: 29.02 | G15: 9197.96 | H15: =IF(D15>G15,0,G15-D15) -> 6186.84 | I15: =IFERROR(H15/D15,0) -> 2.054664
B16: Business & Consumer Services | C16: 162 | D16: 8152.71 | E16: 13637.17 | F16: 59.78 | G16: 20753.97 | H16: =IF(D16>G16,0,G16-D16) -> 12601.26 | I16: =IFERROR(H16/D16,0) -> 1.5456529
B17: Cable TV | C17: 10 | D17: 5197 | E17: 23701.3 | F17: 21.93 | G17: 20472.1 | H17: =IF(D17>G17,0,G17-D17) -> 15275.1 | I17: =IFERROR(H17/D17,0) -> 2.9392149
B18: Chemical (Basic) | C18: 32 | D18: 5979.3 | E18: 4555.08 | F18: 131.27 | G18: 8011.66 | H18: =IF(D18>G18,0,G18-D18) -> 2032.36 | I18: =IFERROR(H18/D18,0) -> 0.33989932
... B78: Retail (Special Lines) | C78: 105 | D78: 6069.07 | E78: 6972.52 | F78: 87.04 | G78: 14754.3 | H78: =IF(D78>G78,0,G78-D78) -> 8685.23 | I78: =IFERROR(H78/D78,0) -> 1.4310644
B79: Rubber& Tires | C79: 3 | D79: 0 | E79: -514.1 | F79: #DIV/0! | G79: 0 | H79: =IF(D79>G79,0,G79-D79) -> 0 | I79: =IFERROR(H79/D79,0) -> 0
B80: Semiconductor | C80: 63 | D80: 23975.2 | E80: 49055.14 | F80: 48.87 | G80: 54855.23 | H80: =IF(D80>G80,0,G80-D80) -> 30880.03 | I80: =IFERROR(H80/D80,0) -> 1.2879988
B81: Semiconductor Equip | C81: 30 | D81: 2940.65 | E81: 14637.39 | F81: 20.09 | G81: 10975.18 | H81: =IF(D81>G81,0,G81-D81) -> 8034.53 | I81: =IFERROR(H81/D81,0) -> 2.7322293
B82: Shipbuilding & Marine | C82: 8 | D82: 169.7 | E82: 578.44 | F82: 29.34 | G82: 680.65 | H82: =IF(D82>G82,0,G82-D82) -> 510.95 | I82: =IFERROR(H82/D82,0) -> 3.0109016
B83: Shoe | C83: 13 | D83: 2218.79 | E83: 6877.56 | F83: 32.26 | G83: 917.52 | H83: =IF(D83>G83,0,G83-D83) -> 0 | I83: =IFERROR(H83/D83,0) -> 0
B84: Software (Entertainment) | C84: 84 | D84: 235.41 | E84: 93923.67 | F84: 0.25 | G84: 90466.02 | H84: =IF(D84>G84,0,G84-D84) -> 90230.61 | I84: =IFERROR(H84/D84,0) -> 383.29132
B85: Software (Internet) | C85: 35 | D85: 0.26 | E85: -4129.53 | F85: 0 | G85: 5130.88 | H85: =IF(D85>G85,0,G85-D85) -> 5130.62 | I85: =IFERROR(H85/D85,0) -> 19733.154
B86: Software (System & Application) | C86: 351 | D86: 26468.85 | E86: 97238.32 | F86: 27.22 | G86: 78137.65 | H86: =IF(D86>G86,0,G86-D86) -> 51668.8 | I86: =IFERROR(H86/D86,0) -> 1.9520606
B87: Steel | C87: 29 | D87: 1786.07 | E87: 14321.58 | F87: 12.47 | G87: 7126.84 | H87: =IF(D87>G87,0,G87-D87) -> 5340.77 | I87: =IFERROR(H87/D87,0) -> 2.9902355
B88: Telecom (Wireless) | C88: 13 | D88: 859.33 | E88: 7780.02 | F88: 11.05 | G88: 13772.85 | H88: =IF(D88>G88,0,G88-D88) -> 12913.52 | I88: =IFERROR(H88/D88,0) -> 15.027428
B89: Telecom. Equipment | C89: 66 | D89: 7386.13 | E89: 16027.25 | F89: 46.08 | G89: 15674.18 | H89: =IF(D89>G89,0,G89-D89) -> 8288.05 | I89: =IFERROR(H89/D89,0) -> 1.12211
B90: Telecom. Services | C90: 42 | D90: 19163.33 | E90: -808.37 | F90: 0.16 | G90: 11908.88 | H90: =IF(D90>G90,0,G90-D90) -> 0 | I90: =IFERROR(H90/D90,0) -> 0
B91: Tobacco | C91: 16 | D91: 14856.91 | E91: 16885.91 | F91: 87.98 | G91: 15977.74 | H91: =IF(D91>G91,0,G91-D91) -> 1120.83 | I91: =IFERROR(H91/D91,0) -> 0.075441663
... B98: Total Market (without financials) | C98: 5214 | D98: 586557.78 | E98: 1421325.2 | F98: 41.27 | G98: 1304851.8 | H98: =IF(D98>G98,0,G98-D98) -> 718294.01 | I98: =IFERROR(H98/D98,0) -> 1.2245921
