Workbook
Name UPDATE: 'Data Sheet'!$E$1

Sheet Data Sheet
A1: COMPANY NAME | B1: TATA MOTORS LTD | E1: =IF(B2<>B3, "A NEW VERSION OF THE WORKSHEET IS AVAILABLE", "")
A2: LATEST VERSION | B2: 2.1 | E2: PLEASE DO NOT MAKE ANY CHANGES TO THIS SHEET
A3: CURRENT VERSION | B3: 2.1
A5: META
A6: Number of shares | B6: =IF(B9>0, B9/B8, 0) -> 366.52542
A7: Face Value | B7: 2
A8: Current Price | B8: 961.8
A9: Market Capitalization | B9: 352524.15
A15: PROFIT & LOSS
A16: Report Date | B16: 42094 | C16: 42460 | D16: 42825 | E16: 43190 | F16: 43555 | G16: 43921 | H16: 44286 | I16: 44651 | J16: 45016 | K16: 45382
A17: Sales | B17: 263158.98 | C17: 273045.6 | D17: 269692.51 | E17: 291550.48 | F17: 301938.4 | G17: 261067.97 | H17: 249794.75 | I17: 278453.62 | J17: 345966.97 | K17: 437927.77
A18: Raw Material Cost | B18: 163250.36 | C18: 166134.01 | D18: 173294.08 | E18: 187896.58 | F18: 194267.91 | G18: 164899.82 | H18: 153607.36 | I18: 179295.33 | J18: 231251.26 | K18: 274321.23
A19: Change in Inventory | B19: 3330.35 | C19: 2750.99 | D19: 7399.92 | E19: 2046.58 | F19: -2053.28 | G19: -2231.19 | H19: -4684.16 | I19: -1590.49 | J19: 4781.62 | K19: 1565.53
A20: Power and Fuel | B20: 1121.75 | C20: 1143.63 | D20: 1159.82 | E20: 1308.08 | F20: 1585.93 | G20: 1264.95 | H20: 1112.87 | I20: 2178.29 | J20: 2513.33 | K20: 2195.12
A21: Other Mfr. Exp | B21: 16173.17 | C21: 12101.53 | D21: 10067.37 | E21: 10971.66 | F21: 11694.54 | G21: 11541.51 | H21: 8273.17 | I21: 9427.38 | J21: 11765.97 | K21: 17114.33
A22: Employee Cost | B22: 25641.95 | C22: 28880.89 | D22: 28332.89 | E22: 30300.09 | F22: 33243.87 | G22: 30438.6 | H22: 27648.48 | I22: 30808.52 | J22: 33654.7 | K22: 42486.64
A23: Selling and admin | B23: 23603.01 | C23: 21991.9 | D23: 30039.38 | E23: 31004.58 | F23: 32719.8 | G23: 29248.32 | H23: 23015.79 | I23: 29205.4 | J23: 34839.19 | K23: 42765.33
A24: Other Expenses | B24: -2539.56 | C24: 7149.38 | D24: 4610.2 | E24: 658.39 | F24: 1708.74 | G24: 3456.51 | H24: -834.51 | I24: 1228.12 | J24: 4908.34 | K24: 1072.31
A25: Other Income | B25: 714.03 | C25: -2669.62 | D25: 1869.1 | E25: 5932.73 | F25: -26686.25 | G25: 101.71 | H25: -11117.83 | I25: 2424.05 | J25: 6663.97 | K25: 5672.66
A26: Depreciation | B26: 13388.63 | C26: 16710.78 | D26: 17904.99 | E26: 21553.59 | F26: 23590.63 | G26: 21425.43 | H26: 23546.71 | I26: 24835.69 | J26: 24860.36 | K26: 27270.13
A27: Interest | B27: 4861.49 | C27: 4889.08 | D27: 4238.01 | E27: 4681.79 | F27: 5758.6 | G27: 7243.33 | H27: 8097.17 | I27: 9311.86 | J27: 10225.48 | K27: 9985.76
... A30: Net profit | B30: 13986.29 | C30: 11579.31 | D30: 7454.36 | E30: 8988.91 | F30: -28826.23 | G30: -12070.85 | H30: -13451.39 | I30: -11441.47 | J30: 2414.29 | K30: 31399.09
A31: Dividend Amount | C31: 67.92 | J31: 766.02 | K31: 4675.65
A40: Quarters
A41: Report Date | B41: 44561 | C41: 44651 | D41: 44742 | E41: 44834 | F41: 44926 | G41: 45016 | H41: 45107 | I41: 45199 | J41: 45291 | K41: 45382
A42: Sales | B42: 72229.29 | C42: 78439.06 | D42: 71934.66 | E42: 79611.37 | F42: 88488.59 | G42: 105932.35 | H42: 102236.08 | I42: 105128.24 | J42: 110577.14 | K42: 119986.31
A43: Expenses | B43: 65151.27 | C43: 70156.27 | D43: 69521.93 | E43: 74039.06 | F43: 77668.35 | G43: 92817.95 | H43: 89018.36 | I43: 91361.3 | J43: 95158.77 | K43: 102851
A44: Other Income | B44: 788.73 | C44: 188.74 | D44: 2380.98 | E44: 1351.14 | F44: 1129.98 | G44: 1452.86 | H44: 683.56 | I44: 1507.05 | J44: 1603.76 | K44: 1618.3
A45: Depreciation | B45: 6078.13 | C45: 6432.11 | D45: 5841.04 | E45: 5897.34 | F45: 6071.78 | G45: 7050.2 | H45: 6633.18 | I45: 6636.42 | J45: 6850 | K45: 7150.53
A46: Interest | B46: 2400.74 | C46: 2380.52 | D46: 2420.72 | E46: 2487.26 | F46: 2675.83 | G46: 2641.67 | H46: 2615.39 | I46: 2651.69 | J46: 2484.91 | K46: 2233.77
A47: Profit before tax | B47: -612.12 | C47: -341.1 | D47: -3468.05 | E47: -1461.15 | F47: 3202.61 | G47: 4875.39 | H47: 4652.71 | I47: 5985.88 | J47: 7687.22 | K47: 9369.31
A48: Tax | B48: 726.05 | C48: 758.22 | D48: 1518.96 | E48: -457.08 | F48: 262.83 | G48: -620.65 | H48: 1563.01 | I48: 2202.84 | J48: 541.79 | K48: -8159.28
A49: Net profit | B49: -1516.14 | C49: -1032.84 | D49: -5006.6 | E49: -944.61 | F49: 2957.71 | G49: 5407.79 | H49: 3202.8 | I49: 3764 | J49: 7025.11 | K49: 17407.18
A50: Operating Profit | B50: 7078.02 | C50: 8282.79 | D50: 2412.73 | E50: 5572.31 | F50: 10820.24 | G50: 13114.4 | H50: 13217.72 | I50: 13766.94 | J50: 15418.37 | K50: 17135.31
A55: BALANCE SHEET
A56: Report Date | B56: 42094 | C56: 42460 | D56: 42825 | E56: 43190 | F56: 43555 | G56: 43921 | H56: 44286 | I56: 44651 | J56: 45016 | K56: 45382
A57: Equity Share Capital | B57: 643.78 | C57: 679.18 | D57: 679.22 | E57: 679.22 | F57: 679.22 | G57: 719.54 | H57: 765.81 | I57: 765.88 | J57: 766.02 | K57: 766.5
A58: Reserves | B58: 55618.14 | C58: 78273.23 | D58: 57382.67 | E58: 94748.69 | F58: 59500.34 | G58: 61491.49 | H58: 54480.91 | I58: 43795.36 | J58: 44555.77 | K58: 84151.52
A59: Borrowings | B59: 73610.39 | C59: 69359.96 | D59: 78603.98 | E59: 88950.47 | F59: 106175.34 | G59: 124787.64 | H59: 142130.57 | I59: 146449.03 | J59: 134113.44 | K59: 107262.5
A60: Other Liabilities | B60: 107442.48 | C60: 114871.75 | D60: 135914.49 | E60: 142813.43 | F60: 139348.59 | G60: 133180.72 | H60: 144192.62 | I60: 138051.22 | J60: 155239.2 | K60: 177340.09
A61: Total | B61: 237314.79 | C61: 263184.12 | D61: 272580.36 | E61: 327191.81 | F61: 305703.49 | G61: 320179.39 | H61: 341569.91 | I61: 329061.49 | J61: 334674.43 | K61: 369520.61
A62: Net Block | B62: 88479.49 | C62: 107231.76 | D62: 95944.08 | E62: 121413.86 | F62: 111234.47 | G62: 127107.14 | H62: 138707.61 | I62: 138855.45 | J62: 132079.76 | K62: 121285.46
A63: Capital Work in Progress | B63: 28640.09 | C63: 25918.94 | D63: 33698.84 | E63: 40033.5 | F63: 31883.84 | G63: 35622.29 | H63: 20963.93 | I63: 10251.09 | J63: 14274.5 | K63: 35698.43
A64: Investments | B64: 15336.74 | C64: 23767.02 | D64: 20337.92 | E64: 20812.75 | F64: 15770.72 | G64: 16308.48 | H64: 24620.28 | I64: 29379.53 | J64: 26379.16 | K64: 22971.07
A65: Other Assets | B65: 104858.47 | C65: 106266.4 | D65: 122599.52 | E65: 144931.7 | F65: 146814.46 | G65: 141141.48 | H65: 157278.09 | I65: 150575.42 | J65: 161941.01 | K65: 189565.65
A66: Total | B66: 237314.79 | C66: 263184.12 | D66: 272580.36 | E66: 327191.81 | F66: 305703.49 | G66: 320179.39 | H66: 341569.91 | I66: 329061.49 | J66: 334674.43 | K66: 369520.61
A67: Receivables | B67: 12579.2 | C67: 13570.91 | D67: 14075.55 | E67: 19893.3 | F67: 18996.17 | G67: 11172.69 | H67: 12679.08 | I67: 12442.12 | J67: 15737.97 | K67: 16951.81
... A70: No. of Equity Shares | B70: 3218930067 | C70: 3395930306 | D70: 3396100719 | E70: 3396100719 | F70: 3396100719 | G70: 3597726185 | H70: 3829060661 | I70: 3829414903 | J70: 3830097221 | K70: 3832491897
A71: New Bonus Shares
A72: Face value | B72: 2 | C72: 2 | D72: 2 | E72: 2 | F72: 2 | G72: 2 | H72: 2 | I72: 2 | J72: 2 | K72: 2
A80: CASH FLOW:
A81: Report Date | B81: 42094 | C81: 42460 | D81: 42825 | E81: 43190 | F81: 43555 | G81: 43921 | H81: 44286 | I81: 44651 | J81: 45016 | K81: 45382
A82: Cash from Operating Activity | B82: 35531.26 | C82: 37899.54 | D82: 30199.25 | E82: 23857.42 | F82: 18890.75 | G82: 26632.94 | H82: 29000.51 | I82: 14282.83 | J82: 35388.01 | K82: 67915.36
A83: Cash from Investing Activity | B83: -36232.35 | C83: -36693.9 | D83: -39571.4 | E83: -25139.14 | F83: -20878.07 | G83: -33114.55 | H83: -25672.5 | I83: -4443.66 | J83: -15417.17 | K83: -22781.56
A84: Cash from Financing Activity | B84: 5201.44 | C84: -3795.12 | D84: 6205.3 | E84: 2011.71 | F84: 8830.37 | G84: 3389.61 | H84: 9904.2 | I84: -3380.17 | J84: -26242.9 | K84: -37005.99
A85: Net Cash Flow | B85: 4500.35 | C85: -2589.48 | D85: -3166.85 | E85: 729.99 | F85: 6843.05 | G85: -3092 | H85: 13232.21 | I85: 6459 | J85: -6272.06 | K85: 8127.81
A90: PRICE: | B90: 544.37 | C90: 386.6 | D90: 465.85 | E90: 326.85 | F90: 174.25 | G90: 71.05 | H90: 301.8 | I90: 433.75 | J90: 420.8 | K90: 992.8
A92: DERIVED:
A93: Adjusted Equity Shares in Cr | B93: 288.74 | C93: 288.72 | D93: 288.73 | E93: 288.73 | F93: 288.73 | G93: 308.9 | H93: 332.03 | I93: 332.07 | J93: 332.13 | K93: 332.37

Sheet Financials>

Sheet HistoricalFS
B2: ="Historical Financial Statement - "&'Data Sheet'!B1 -> Historical Financial Statement - TATA MOTORS LTD
B3: Years | C3: ='Data Sheet'!B16 -> 42094 | D3: ='Data Sheet'!C16 -> 42460 | E3: ='Data Sheet'!D16 -> 42825 | F3: ='Data Sheet'!E16 -> 43190 | G3: ='Data Sheet'!F16 -> 43555 | H3: ='Data Sheet'!G16 -> 43921 | I3: ='Data Sheet'!H16 -> 44286 | J3: ='Data Sheet'!I16 -> 44651 | ... L3: ='Data Sheet'!K16 -> 45382 | M3: LTM
A4: # | B4: Income Statement (Crores)
B5: Sales | C5: =IFERROR('Data Sheet'!B17,0) -> 263158.98 | D5: =IFERROR('Data Sheet'!C17,0) -> 273045.6 | E5: =IFERROR('Data Sheet'!D17,0) -> 269692.51 | F5: =IFERROR('Data Sheet'!E17,0) -> 291550.48 | G5: =IFERROR('Data Sheet'!F17,0) -> 301938.4 | H5: =IFERROR('Data Sheet'!G17,0) -> 261067.97 | I5: =IFERROR('Data Sheet'!H17,0) -> 249794.75 | J5: =IFERROR('Data Sheet'!I17,0) -> 278453.62 | ... L5: =IFERROR('Data Sheet'!K17,0) -> 437927.77 | M5: =IFERROR(SUM('Data Sheet'!H17:K17),0) -> 1312143.1
B6: Sales Growth | C6: - | D6: =D5/C5-1 -> 0.037569001 | E6: =E5/D5-1 -> -0.01228033 | F6: =F5/E5-1 -> 0.081047746 | G6: =G5/F5-1 -> 0.035629919 | H6: =H5/G5-1 -> -0.13536016 | I6: =I5/H5-1 -> -0.043181168 | J6: =J5/I5-1 -> 0.11472967 | K6: =K5/J5-1 -> 0.24245815 | L6: =L5/K5-1 -> 0.26580803
B8: COGS | C8: =IFERROR(SUM('Data Sheet'!B18:B22)-1*'Data Sheet'!B19,0) -> 206187.23 | D8: =IFERROR(SUM('Data Sheet'!C18:C22)-1*'Data Sheet'!C19,0) -> 208260.06 | E8: =IFERROR(SUM('Data Sheet'!D18:D22)-1*'Data Sheet'!D19,0) -> 212854.16 | F8: =IFERROR(SUM('Data Sheet'!E18:E22)-1*'Data Sheet'!E19,0) -> 230476.41 | G8: =IFERROR(SUM('Data Sheet'!F18:F22)-1*'Data Sheet'!F19,0) -> 240792.25 | H8: =IFERROR(SUM('Data Sheet'!G18:G22)-1*'Data Sheet'!G19,0) -> 208144.88 | I8: =IFERROR(SUM('Data Sheet'!H18:H22)-1*'Data Sheet'!H19,0) -> 190641.88 | J8: =IFERROR(SUM('Data Sheet'!I18:I22)-1*'Data Sheet'!I19,0) -> 221709.52 | ... L8: =IFERROR(SUM('Data Sheet'!K18:K22)-1*'Data Sheet'!K19,0) -> 336117.32
B9: COGS%Sales | C9: =C8/C5 -> 0.78350824 | D9: =D8/D5 -> 0.76272996 | E9: =E8/E5 -> 0.78924758 | F9: =F8/F5 -> 0.79051974 | G9: =G8/G5 -> 0.797488 | H9: =H8/H5 -> 0.79728233 | I9: =I8/I5 -> 0.7631941 | J9: =J8/J5 -> 0.79621705 | ... L9: =L8/L5 -> 0.76751771
B11: Gross Profit | C11: =C5-C8 -> 56971.75 | D11: =D5-D8 -> 64785.54 | E11: =E5-E8 -> 56838.35 | F11: =F5-F8 -> 61074.07 | G11: =G5-G8 -> 61146.15 | H11: =H5-H8 -> 52923.09 | I11: =I5-I8 -> 59152.87 | J11: =J5-J8 -> 56744.1 | ... L11: =L5-L8 -> 101810.45
B12: Gross Margin | C12: =C11/C5 -> 0.21649176 | D12: =D11/D5 -> 0.23727004 | E12: =E11/E5 -> 0.21075242 | F12: =F11/F5 -> 0.20948026 | G12: =G11/G5 -> 0.202512 | H12: =H11/H5 -> 0.20271767 | I12: =I11/I5 -> 0.2368059 | J12: =J11/J5 -> 0.20378295 | ... L12: =L11/L5 -> 0.23248229
B14: SG&A | C14: =IFERROR(SUM('Data Sheet'!B23:B24),0) -> 21063.45 | D14: =IFERROR(SUM('Data Sheet'!C23:C24),0) -> 29141.28 | E14: =IFERROR(SUM('Data Sheet'!D23:D24),0) -> 34649.58 | F14: =IFERROR(SUM('Data Sheet'!E23:E24),0) -> 31662.97 | G14: =IFERROR(SUM('Data Sheet'!F23:F24),0) -> 34428.54 | H14: =IFERROR(SUM('Data Sheet'!G23:G24),0) -> 32704.83 | I14: =IFERROR(SUM('Data Sheet'!H23:H24),0) -> 22181.28 | J14: =IFERROR(SUM('Data Sheet'!I23:I24),0) -> 30433.52 | ... L14: =IFERROR(SUM('Data Sheet'!K23:K24),0) -> 43837.64
B15: S&G Exp % Sales | C15: =C14/C5 -> 0.08004078 | D15: =D14/D5 -> 0.10672679 | E15: =E14/E5 -> 0.1284781 | F15: =F14/F5 -> 0.10860202 | G15: =G14/G5 -> 0.11402505 | H15: =H14/H5 -> 0.12527324 | I15: =I14/I5 -> 0.088798023 | J15: =J14/J5 -> 0.10929475 | ... L15: =L14/L5 -> 0.10010244
B17: EBITDA | C17: =C11-C14 -> 35908.3 | D17: =D11-D14 -> 35644.26 | E17: =E11-E14 -> 22188.77 | F17: =F11-F14 -> 29411.1 | G17: =G11-G14 -> 26717.61 | H17: =H11-H14 -> 20218.26 | I17: =I11-I14 -> 36971.59 | J17: =J11-J14 -> 26310.58 | ... L17: =L11-L14 -> 57972.81
B18: EBITDA Margin | C18: =C17/C5 -> 0.13645098 | D18: =D17/D5 -> 0.13054325 | E18: =E17/E5 -> 0.082274328 | F18: =F17/F5 -> 0.10087824 | G18: =G17/G5 -> 0.088486956 | H18: =H17/H5 -> 0.07744443 | I18: =I17/I5 -> 0.14800787 | J18: =J17/J5 -> 0.094488195 | ... L18: =L17/L5 -> 0.13237984
B20: Interest | C20: =IFERROR('Data Sheet'!B27,0) -> 4861.49 | D20: =IFERROR('Data Sheet'!C27,0) -> 4889.08 | E20: =IFERROR('Data Sheet'!D27,0) -> 4238.01 | F20: =IFERROR('Data Sheet'!E27,0) -> 4681.79 | G20: =IFERROR('Data Sheet'!F27,0) -> 5758.6 | H20: =IFERROR('Data Sheet'!G27,0) -> 7243.33 | I20: =IFERROR('Data Sheet'!H27,0) -> 8097.17 | J20: =IFERROR('Data Sheet'!I27,0) -> 9311.86 | ... L20: =IFERROR('Data Sheet'!K27,0) -> 9985.76
B21: Interest % Sales | C21: =C20/C5 -> 0.018473586 | D21: =D20/D5 -> 0.017905727 | E21: =E20/E5 -> 0.01571423 | F21: =F20/F5 -> 0.016058248 | G21: =G20/G5 -> 0.019072102 | H21: =H20/H5 -> 0.027744997 | I21: =I20/I5 -> 0.032415293 | J21: =J20/J5 -> 0.033441332 | ... L21: =L20/L5 -> 0.022802299
B23: Depreciation | C23: =IFERROR('Data Sheet'!B26,0) -> 13388.63 | D23: =IFERROR('Data Sheet'!C26,0) -> 16710.78 | E23: =IFERROR('Data Sheet'!D26,0) -> 17904.99 | F23: =IFERROR('Data Sheet'!E26,0) -> 21553.59 | G23: =IFERROR('Data Sheet'!F26,0) -> 23590.63 | H23: =IFERROR('Data Sheet'!G26,0) -> 21425.43 | I23: =IFERROR('Data Sheet'!H26,0) -> 23546.71 | J23: =IFERROR('Data Sheet'!I26,0) -> 24835.69 | ... L23: =IFERROR('Data Sheet'!K26,0) -> 27270.13
B24: Depriciation % sales | C24: =C23/C5 -> 0.050876584 | D24: =D23/D5 -> 0.061201426 | E24: =E23/E5 -> 0.066390387 | F24: =F23/F5 -> 0.073927472 | G24: =G23/G5 -> 0.078130605 | H24: =H23/H5 -> 0.082068398 | I24: =I23/I5 -> 0.094264231 | J24: =J23/J5 -> 0.089191478 | ... L24: =L23/L5 -> 0.06227084
B26: EBT | C26: =IFERROR(C17-(SUM(C20,C23)),0) -> 17658.18 | D26: =IFERROR(D17-(SUM(D20,D23)),0) -> 14044.4 | E26: =IFERROR(E17-(SUM(E20,E23)),0) -> 45.77 | F26: =IFERROR(F17-(SUM(F20,F23)),0) -> 3175.72 | G26: =IFERROR(G17-(SUM(G20,G23)),0) -> -2631.62 | H26: =IFERROR(H17-(SUM(H20,H23)),0) -> -8450.5 | I26: =IFERROR(I17-(SUM(I20,I23)),0) -> 5327.71 | J26: =IFERROR(J17-(SUM(J20,J23)),0) -> -7836.97 | ... L26: =IFERROR(L17-(SUM(L20,L23)),0) -> 20716.92
B27: EBT % sales | C27: =C26/C5 -> 0.067100807 | D27: =D26/D5 -> 0.051436097 | E27: =E26/E5 -> 0.0001697118 | F27: =F26/F5 -> 0.010892522 | G27: =G26/G5 -> -0.0087157513 | H27: =H26/H5 -> -0.032368965 | I27: =I26/I5 -> 0.021328351 | J27: =J26/J5 -> -0.028144615 | ... L27: =L26/L5 -> 0.047306705
B29: Tax | C29: =IFERROR('Data Sheet'!B29,0) -> 7642.91 | D29: =IFERROR('Data Sheet'!C29,0) -> 3025.05 | E29: =IFERROR('Data Sheet'!D29,0) -> 3251.23 | F29: =IFERROR('Data Sheet'!E29,0) -> 4341.93 | G29: =IFERROR('Data Sheet'!F29,0) -> -2437.45 | H29: =IFERROR('Data Sheet'!G29,0) -> 395.25 | I29: =IFERROR('Data Sheet'!H29,0) -> 2541.86 | J29: =IFERROR('Data Sheet'!I29,0) -> 4231.29 | ... L29: =IFERROR('Data Sheet'!K29,0) -> -3851.64
B30: Effective Tax Rate | C30: =C29/C26 -> 0.43282547 | D30: =D29/D26 -> 0.2153919 | E30: =E29/E26 -> 71.034083 | F30: =F29/F26 -> 1.367227 | G30: =G29/G26 -> 0.92621655 | H30: =H29/H26 -> -0.04677238 | I30: =I29/I26 -> 0.47710179 | J30: =J29/J26 -> -0.53991402 | ... L30: =L29/L26 -> -0.1859176
B32: Net Profit | C32: =IFERROR(C26-C29,0) -> 10015.27 | D32: =IFERROR(D26-D29,0) -> 11019.35 | E32: =IFERROR(E26-E29,0) -> -3205.46 | F32: =IFERROR(F26-F29,0) -> -1166.21 | G32: =IFERROR(G26-G29,0) -> -194.17 | H32: =IFERROR(H26-H29,0) -> -8845.75 | I32: =IFERROR(I26-I29,0) -> 2785.85 | J32: =IFERROR(J26-J29,0) -> -12068.26 | ... L32: =IFERROR(L26-L29,0) -> 24568.56
B33: Net Margin | C33: =C32/C5 -> 0.038057869 | D33: =D32/D5 -> 0.040357178 | E33: =E32/E5 -> -0.01188561 | F33: =F32/F5 -> -0.0040000277 | G33: =G32/G5 -> -0.00064307819 | H33: =H32/H5 -> -0.033882939 | I33: =I32/I5 -> 0.011152556 | J33: =J32/J5 -> -0.043340288 | ... L33: =L32/L5 -> 0.056101854
B35: No of Equity Shares | C35: ='Data Sheet'!B93 -> 288.74 | D35: ='Data Sheet'!C93 -> 288.72 | E35: ='Data Sheet'!D93 -> 288.73 | F35: ='Data Sheet'!E93 -> 288.73 | G35: ='Data Sheet'!F93 -> 288.73 | H35: ='Data Sheet'!G93 -> 308.9 | I35: ='Data Sheet'!H93 -> 332.03 | J35: ='Data Sheet'!I93 -> 332.07 | ... L35: ='Data Sheet'!K93 -> 332.37
B37: EPS | C37: =IFERROR(C32/C35,0) -> 34.686119 | D37: =IFERROR(D32/D35,0) -> 38.166216 | E37: =IFERROR(E32/E35,0) -> -11.101929 | F37: =IFERROR(F32/F35,0) -> -4.0391023 | G37: =IFERROR(G32/G35,0) -> -0.6724968 | H37: =IFERROR(H32/H35,0) -> -28.63629 | I37: =IFERROR(I32/I35,0) -> 8.3903563 | J37: =IFERROR(J32/J35,0) -> -36.342518 | ... L37: =IFERROR(L32/L35,0) -> 73.919307
B39: Dividend | C39: =IFERROR('Data Sheet'!B31/HistoricalFS!C35,0) -> 0 | D39: =IFERROR('Data Sheet'!C31/HistoricalFS!D35,0) -> 0.23524522 | E39: =IFERROR('Data Sheet'!D31/HistoricalFS!E35,0) -> 0 | F39: =IFERROR('Data Sheet'!E31/HistoricalFS!F35,0) -> 0 | G39: =IFERROR('Data Sheet'!F31/HistoricalFS!G35,0) -> 0 | H39: =IFERROR('Data Sheet'!G31/HistoricalFS!H35,0) -> 0 | I39: =IFERROR('Data Sheet'!H31/HistoricalFS!I35,0) -> 0 | J39: =IFERROR('Data Sheet'!I31/HistoricalFS!J35,0) -> 0 | ... L39: =IFERROR('Data Sheet'!K31/HistoricalFS!L35,0) -> 14.067605
B40: Dividend Payout Ratio | C40: =IFERROR(C39/C37,0) -> 0 | D40: =IFERROR(D39/D37,0) -> 0.0061637029 | E40: =IFERROR(E39/E37,0) -> 0 | F40: =IFERROR(F39/F37,0) -> 0 | G40: =IFERROR(G39/G37,0) -> 0 | H40: =IFERROR(H39/H37,0) -> 0 | I40: =IFERROR(I39/I37,0) -> 0 | J40: =IFERROR(J39/J37,0) -> 0 | ... L40: =IFERROR(L39/L37,0) -> 0.1903103
B42: Retained Earnings | C42: =IFERROR(IF(C40<0, 1+C40,1-C40),0) -> 1 | D42: =IFERROR(IF(D40<0, 1+D40,1-D40),0) -> 0.9938363 | E42: =IFERROR(IF(E40<0, 1+E40,1-E40),0) -> 1 | F42: =IFERROR(IF(F40<0, 1+F40,1-F40),0) -> 1 | G42: =IFERROR(IF(G40<0, 1+G40,1-G40),0) -> 1 | H42: =IFERROR(IF(H40<0, 1+H40,1-H40),0) -> 1 | I42: =IFERROR(IF(I40<0, 1+I40,1-I40),0) -> 1 | J42: =IFERROR(IF(J40<0, 1+J40,1-J40),0) -> 1 | ... L42: =IFERROR(IF(L40<0, 1+L40,1-L40),0) -> 0.8096897
A44: # | B44: Balance Sheet
B45: Equity Share Capital | C45: =IFERROR('Data Sheet'!B57,0) -> 643.78 | D45: =IFERROR('Data Sheet'!C57,0) -> 679.18 | E45: =IFERROR('Data Sheet'!D57,0) -> 679.22 | F45: =IFERROR('Data Sheet'!E57,0) -> 679.22 | G45: =IFERROR('Data Sheet'!F57,0) -> 679.22 | H45: =IFERROR('Data Sheet'!G57,0) -> 719.54 | I45: =IFERROR('Data Sheet'!H57,0) -> 765.81 | J45: =IFERROR('Data Sheet'!I57,0) -> 765.88 | ... L45: =IFERROR('Data Sheet'!K57,0) -> 766.5
B46: Reserves | C46: =IFERROR('Data Sheet'!B58,0) -> 55618.14 | D46: =IFERROR('Data Sheet'!C58,0) -> 78273.23 | E46: =IFERROR('Data Sheet'!D58,0) -> 57382.67 | F46: =IFERROR('Data Sheet'!E58,0) -> 94748.69 | G46: =IFERROR('Data Sheet'!F58,0) -> 59500.34 | H46: =IFERROR('Data Sheet'!G58,0) -> 61491.49 | I46: =IFERROR('Data Sheet'!H58,0) -> 54480.91 | J46: =IFERROR('Data Sheet'!I58,0) -> 43795.36 | ... L46: =IFERROR('Data Sheet'!K58,0) -> 84151.52
B47: Borrowings | C47: =IFERROR('Data Sheet'!B59,0) -> 73610.39 | D47: =IFERROR('Data Sheet'!C59,0) -> 69359.96 | E47: =IFERROR('Data Sheet'!D59,0) -> 78603.98 | F47: =IFERROR('Data Sheet'!E59,0) -> 88950.47 | G47: =IFERROR('Data Sheet'!F59,0) -> 106175.34 | H47: =IFERROR('Data Sheet'!G59,0) -> 124787.64 | I47: =IFERROR('Data Sheet'!H59,0) -> 142130.57 | J47: =IFERROR('Data Sheet'!I59,0) -> 146449.03 | ... L47: =IFERROR('Data Sheet'!K59,0) -> 107262.5
B48: Other Liabilities | C48: =IFERROR('Data Sheet'!B60,0) -> 107442.48 | D48: =IFERROR('Data Sheet'!C60,0) -> 114871.75 | E48: =IFERROR('Data Sheet'!D60,0) -> 135914.49 | F48: =IFERROR('Data Sheet'!E60,0) -> 142813.43 | G48: =IFERROR('Data Sheet'!F60,0) -> 139348.59 | H48: =IFERROR('Data Sheet'!G60,0) -> 133180.72 | I48: =IFERROR('Data Sheet'!H60,0) -> 144192.62 | J48: =IFERROR('Data Sheet'!I60,0) -> 138051.22 | ... L48: =IFERROR('Data Sheet'!K60,0) -> 177340.09
B49: Total Liabilities | C49: =IFERROR('Data Sheet'!B61,0) -> 237314.79 | D49: =IFERROR('Data Sheet'!C61,0) -> 263184.12 | E49: =IFERROR('Data Sheet'!D61,0) -> 272580.36 | F49: =IFERROR('Data Sheet'!E61,0) -> 327191.81 | G49: =IFERROR('Data Sheet'!F61,0) -> 305703.49 | H49: =IFERROR('Data Sheet'!G61,0) -> 320179.39 | I49: =IFERROR('Data Sheet'!H61,0) -> 341569.91 | J49: =IFERROR('Data Sheet'!I61,0) -> 329061.49 | ... L49: =IFERROR('Data Sheet'!K61,0) -> 369520.61
B51: Net Block | C51: =IFERROR('Data Sheet'!B62,0) -> 88479.49 | D51: =IFERROR('Data Sheet'!C62,0) -> 107231.76 | E51: =IFERROR('Data Sheet'!D62,0) -> 95944.08 | F51: =IFERROR('Data Sheet'!E62,0) -> 121413.86 | G51: =IFERROR('Data Sheet'!F62,0) -> 111234.47 | H51: =IFERROR('Data Sheet'!G62,0) -> 127107.14 | I51: =IFERROR('Data Sheet'!H62,0) -> 138707.61 | J51: =IFERROR('Data Sheet'!I62,0) -> 138855.45 | ... L51: =IFERROR('Data Sheet'!K62,0) -> 121285.46
B52: Capital Work in Progress | C52: =IFERROR('Data Sheet'!B63,0) -> 28640.09 | D52: =IFERROR('Data Sheet'!C63,0) -> 25918.94 | E52: =IFERROR('Data Sheet'!D63,0) -> 33698.84 | F52: =IFERROR('Data Sheet'!E63,0) -> 40033.5 | G52: =IFERROR('Data Sheet'!F63,0) -> 31883.84 | H52: =IFERROR('Data Sheet'!G63,0) -> 35622.29 | I52: =IFERROR('Data Sheet'!H63,0) -> 20963.93 | J52: =IFERROR('Data Sheet'!I63,0) -> 10251.09 | ... L52: =IFERROR('Data Sheet'!K63,0) -> 35698.43
B53: Investments | C53: =IFERROR('Data Sheet'!B64,0) -> 15336.74 | D53: =IFERROR('Data Sheet'!C64,0) -> 23767.02 | E53: =IFERROR('Data Sheet'!D64,0) -> 20337.92 | F53: =IFERROR('Data Sheet'!E64,0) -> 20812.75 | G53: =IFERROR('Data Sheet'!F64,0) -> 15770.72 | H53: =IFERROR('Data Sheet'!G64,0) -> 16308.48 | I53: =IFERROR('Data Sheet'!H64,0) -> 24620.28 | J53: =IFERROR('Data Sheet'!I64,0) -> 29379.53 | ... L53: =IFERROR('Data Sheet'!K64,0) -> 22971.07
B54: Other Assets | C54: =IFERROR('Data Sheet'!B65,0) -> 104858.47 | D54: =IFERROR('Data Sheet'!C65,0) -> 106266.4 | E54: =IFERROR('Data Sheet'!D65,0) -> 122599.52 | F54: =IFERROR('Data Sheet'!E65,0) -> 144931.7 | G54: =IFERROR('Data Sheet'!F65,0) -> 146814.46 | H54: =IFERROR('Data Sheet'!G65,0) -> 141141.48 | I54: =IFERROR('Data Sheet'!H65,0) -> 157278.09 | J54: =IFERROR('Data Sheet'!I65,0) -> 150575.42 | ... L54: =IFERROR('Data Sheet'!K65,0) -> 189565.65
B55: Total Assets | C55: =IFERROR('Data Sheet'!B66,0) -> 237314.79 | D55: =IFERROR('Data Sheet'!C66,0) -> 263184.12 | E55: =IFERROR('Data Sheet'!D66,0) -> 272580.36 | F55: =IFERROR('Data Sheet'!E66,0) -> 327191.81 | G55: =IFERROR('Data Sheet'!F66,0) -> 305703.49 | H55: =IFERROR('Data Sheet'!G66,0) -> 320179.39 | I55: =IFERROR('Data Sheet'!H66,0) -> 341569.91 | J55: =IFERROR('Data Sheet'!I66,0) -> 329061.49 | ... L55: =IFERROR('Data Sheet'!K66,0) -> 369520.61
B57: Receivables | C57: =IFERROR('Data Sheet'!B67,0) -> 12579.2 | D57: =IFERROR('Data Sheet'!C67,0) -> 13570.91 | E57: =IFERROR('Data Sheet'!D67,0) -> 14075.55 | F57: =IFERROR('Data Sheet'!E67,0) -> 19893.3 | G57: =IFERROR('Data Sheet'!F67,0) -> 18996.17 | H57: =IFERROR('Data Sheet'!G67,0) -> 11172.69 | I57: =IFERROR('Data Sheet'!H67,0) -> 12679.08 | J57: =IFERROR('Data Sheet'!I67,0) -> 12442.12 | ... L57: =IFERROR('Data Sheet'!K67,0) -> 16951.81
B58: Inventory | C58: =IFERROR('Data Sheet'!B68,0) -> 29272.34 | D58: =IFERROR('Data Sheet'!C68,0) -> 32655.73 | E58: =IFERROR('Data Sheet'!D68,0) -> 35085.31 | F58: =IFERROR('Data Sheet'!E68,0) -> 42137.63 | G58: =IFERROR('Data Sheet'!F68,0) -> 39013.73 | H58: =IFERROR('Data Sheet'!G68,0) -> 37456.88 | I58: =IFERROR('Data Sheet'!H68,0) -> 36088.59 | J58: =IFERROR('Data Sheet'!I68,0) -> 35240.34 | ... L58: =IFERROR('Data Sheet'!K68,0) -> 47788.29
B59: Cash & Bank | C59: =IFERROR('Data Sheet'!B69,0) -> 32115.76 | D59: =IFERROR('Data Sheet'!C69,0) -> 30460.4 | E59: =IFERROR('Data Sheet'!D69,0) -> 36077.88 | F59: =IFERROR('Data Sheet'!E69,0) -> 34613.91 | G59: =IFERROR('Data Sheet'!F69,0) -> 32648.82 | H59: =IFERROR('Data Sheet'!G69,0) -> 33726.97 | I59: =IFERROR('Data Sheet'!H69,0) -> 46792.46 | J59: =IFERROR('Data Sheet'!I69,0) -> 40669.19 | ... L59: =IFERROR('Data Sheet'!K69,0) -> 45806.69
B60: No. of Equity Shares | C60: =IFERROR('Data Sheet'!B70,0) -> 3218930067 | D60: =IFERROR('Data Sheet'!C70,0) -> 3395930306 | E60: =IFERROR('Data Sheet'!D70,0) -> 3396100719 | F60: =IFERROR('Data Sheet'!E70,0) -> 3396100719 | G60: =IFERROR('Data Sheet'!F70,0) -> 3396100719 | H60: =IFERROR('Data Sheet'!G70,0) -> 3597726185 | I60: =IFERROR('Data Sheet'!H70,0) -> 3829060661 | J60: =IFERROR('Data Sheet'!I70,0) -> 3829414903 | ... L60: =IFERROR('Data Sheet'!K70,0) -> 3832491897
B62: A=L+E | C62: =C55=C49 -> TRUE | D62: =D55=D49 -> TRUE | E62: =E55=E49 -> TRUE | F62: =F55=F49 -> TRUE | G62: =G55=G49 -> TRUE | H62: =H55=H49 -> TRUE | I62: =I55=I49 -> TRUE | J62: =J55=J49 -> TRUE | ... L62: =L55=L49 -> TRUE
A64: # | B64: Cash Flow Statement
B65: Cash from Operating Activity - | C65: =IFERROR('Cash Flow Data'!E4,0) -> 35531 | D65: =IFERROR('Cash Flow Data'!F4,0) -> 37900 | E65: =IFERROR('Cash Flow Data'!G4,0) -> 30199 | F65: =IFERROR('Cash Flow Data'!H4,0) -> 23857 | G65: =IFERROR('Cash Flow Data'!I4,0) -> 18891 | H65: =IFERROR('Cash Flow Data'!J4,0) -> 26633 | I65: =IFERROR('Cash Flow Data'!K4,0) -> 29001 | J65: =IFERROR('Cash Flow Data'!L4,0) -> 14283 | ... L65: =IFERROR('Cash Flow Data'!N4,0) -> 67915
B66: Profit from operations | C66: =IFERROR('Cash Flow Data'!E5,0) -> 43397 | D66: =IFERROR('Cash Flow Data'!F5,0) -> 38626 | E66: =IFERROR('Cash Flow Data'!G5,0) -> 28840 | F66: =IFERROR('Cash Flow Data'!H5,0) -> 33312 | G66: =IFERROR('Cash Flow Data'!I5,0) -> 28771 | H66: =IFERROR('Cash Flow Data'!J5,0) -> 23352 | I66: =IFERROR('Cash Flow Data'!K5,0) -> 31198 | J66: =IFERROR('Cash Flow Data'!L5,0) -> 26943 | ... L66: =IFERROR('Cash Flow Data'!N5,0) -> 65106
B67: Receivables | C67: =IFERROR('Cash Flow Data'!E6,0) -> -3179 | D67: =IFERROR('Cash Flow Data'!F6,0) -> -2223 | E67: =IFERROR('Cash Flow Data'!G6,0) -> -4152 | F67: =IFERROR('Cash Flow Data'!H6,0) -> -10688 | G67: =IFERROR('Cash Flow Data'!I6,0) -> -9109 | H67: =IFERROR('Cash Flow Data'!J6,0) -> 9950 | I67: =IFERROR('Cash Flow Data'!K6,0) -> -5505 | J67: =IFERROR('Cash Flow Data'!L6,0) -> 185 | ... L67: =IFERROR('Cash Flow Data'!N6,0) -> -1875
B68: Inventory | C68: =IFERROR('Cash Flow Data'!E7,0) -> -3692 | D68: =IFERROR('Cash Flow Data'!F7,0) -> -5743 | E68: =IFERROR('Cash Flow Data'!G7,0) -> -6621 | F68: =IFERROR('Cash Flow Data'!H7,0) -> -3560 | G68: =IFERROR('Cash Flow Data'!I7,0) -> 2069 | H68: =IFERROR('Cash Flow Data'!J7,0) -> 2326 | I68: =IFERROR('Cash Flow Data'!K7,0) -> 3814 | J68: =IFERROR('Cash Flow Data'!L7,0) -> 472 | ... L68: =IFERROR('Cash Flow Data'!N7,0) -> -7265
B69: Payables | C69: =IFERROR('Cash Flow Data'!E8,0) -> 3598 | D69: =IFERROR('Cash Flow Data'!F8,0) -> 3947 | E69: =IFERROR('Cash Flow Data'!G8,0) -> 9301 | F69: =IFERROR('Cash Flow Data'!H8,0) -> 7320 | G69: =IFERROR('Cash Flow Data'!I8,0) -> -4692 | H69: =IFERROR('Cash Flow Data'!J8,0) -> -8085 | I69: =IFERROR('Cash Flow Data'!K8,0) -> 5748 | J69: =IFERROR('Cash Flow Data'!L8,0) -> -7012 | ... L69: =IFERROR('Cash Flow Data'!N8,0) -> 13706
B70: Loans Advances | C70: =IFERROR('Cash Flow Data'!E9,0) -> 0 | D70: =IFERROR('Cash Flow Data'!F9,0) -> -520 | E70: =IFERROR('Cash Flow Data'!G9,0) -> 0 | F70: =IFERROR('Cash Flow Data'!H9,0) -> 0 | G70: =IFERROR('Cash Flow Data'!I9,0) -> 0 | H70: =IFERROR('Cash Flow Data'!J9,0) -> 0 | I70: =IFERROR('Cash Flow Data'!K9,0) -> 0 | J70: =IFERROR('Cash Flow Data'!L9,0) -> 0 | ... L70: =IFERROR('Cash Flow Data'!N9,0) -> 0
B71: Other WC items | C71: =IFERROR('Cash Flow Data'!E10,0) -> -398 | D71: =IFERROR('Cash Flow Data'!F10,0) -> 5852 | E71: =IFERROR('Cash Flow Data'!G10,0) -> 4727 | F71: =IFERROR('Cash Flow Data'!H10,0) -> 494 | G71: =IFERROR('Cash Flow Data'!I10,0) -> 4512 | H71: =IFERROR('Cash Flow Data'!J10,0) -> 875 | I71: =IFERROR('Cash Flow Data'!K10,0) -> -4150 | J71: =IFERROR('Cash Flow Data'!L10,0) -> -4396 | ... L71: =IFERROR('Cash Flow Data'!N10,0) -> 2760
B72: Working capital changes | C72: =IFERROR('Cash Flow Data'!E11,0) -> -3672 | D72: =IFERROR('Cash Flow Data'!F11,0) -> 1313 | E72: =IFERROR('Cash Flow Data'!G11,0) -> 3254 | F72: =IFERROR('Cash Flow Data'!H11,0) -> -6434 | G72: =IFERROR('Cash Flow Data'!I11,0) -> -7221 | H72: =IFERROR('Cash Flow Data'!J11,0) -> 5065 | I72: =IFERROR('Cash Flow Data'!K11,0) -> -93 | J72: =IFERROR('Cash Flow Data'!L11,0) -> -10750 | ... L72: =IFERROR('Cash Flow Data'!N11,0) -> 7325
B73: Direct taxes | C73: =IFERROR('Cash Flow Data'!E12,0) -> -4194 | D73: =IFERROR('Cash Flow Data'!F12,0) -> -2040 | E73: =IFERROR('Cash Flow Data'!G12,0) -> -1895 | F73: =IFERROR('Cash Flow Data'!H12,0) -> -3021 | G73: =IFERROR('Cash Flow Data'!I12,0) -> -2659 | H73: =IFERROR('Cash Flow Data'!J12,0) -> -1785 | I73: =IFERROR('Cash Flow Data'!K12,0) -> -2105 | J73: =IFERROR('Cash Flow Data'!L12,0) -> -1910 | ... L73: =IFERROR('Cash Flow Data'!N12,0) -> -4516
B75: Cash from Investing Activity - | C75: =IFERROR('Cash Flow Data'!E13,0) -> -36232 | D75: =IFERROR('Cash Flow Data'!F13,0) -> -36694 | E75: =IFERROR('Cash Flow Data'!G13,0) -> -39571 | F75: =IFERROR('Cash Flow Data'!H13,0) -> -25139 | G75: =IFERROR('Cash Flow Data'!I13,0) -> -20878 | H75: =IFERROR('Cash Flow Data'!J13,0) -> -33115 | I75: =IFERROR('Cash Flow Data'!K13,0) -> -25672 | J75: =IFERROR('Cash Flow Data'!L13,0) -> -4444 | ... L75: =IFERROR('Cash Flow Data'!N13,0) -> -22782
B76: Fixed assets purchased | C76: =IFERROR('Cash Flow Data'!E14,0) -> -31962 | D76: =IFERROR('Cash Flow Data'!F14,0) -> -31503 | E76: =IFERROR('Cash Flow Data'!G14,0) -> -16072 | F76: =IFERROR('Cash Flow Data'!H14,0) -> -35079 | G76: =IFERROR('Cash Flow Data'!I14,0) -> -35304 | H76: =IFERROR('Cash Flow Data'!J14,0) -> -29702 | I76: =IFERROR('Cash Flow Data'!K14,0) -> -20205 | J76: =IFERROR('Cash Flow Data'!L14,0) -> -15168 | ... L76: =IFERROR('Cash Flow Data'!N14,0) -> -31414
B77: Fixed assets sold | C77: =IFERROR('Cash Flow Data'!E15,0) -> 74 | D77: =IFERROR('Cash Flow Data'!F15,0) -> 59 | E77: =IFERROR('Cash Flow Data'!G15,0) -> 53 | F77: =IFERROR('Cash Flow Data'!H15,0) -> 30 | G77: =IFERROR('Cash Flow Data'!I15,0) -> 67 | H77: =IFERROR('Cash Flow Data'!J15,0) -> 171 | I77: =IFERROR('Cash Flow Data'!K15,0) -> 351 | J77: =IFERROR('Cash Flow Data'!L15,0) -> 230 | ... L77: =IFERROR('Cash Flow Data'!N15,0) -> 231
B78: Investments purchased | C78: =IFERROR('Cash Flow Data'!E16,0) -> -5461 | D78: =IFERROR('Cash Flow Data'!F16,0) -> -4728 | E78: =IFERROR('Cash Flow Data'!G16,0) -> -6 | F78: =IFERROR('Cash Flow Data'!H16,0) -> -329 | G78: =IFERROR('Cash Flow Data'!I16,0) -> -130 | H78: =IFERROR('Cash Flow Data'!J16,0) -> -1439 | I78: =IFERROR('Cash Flow Data'!K16,0) -> -7530 | J78: =IFERROR('Cash Flow Data'!L16,0) -> -3008 | ... L78: =IFERROR('Cash Flow Data'!N16,0) -> -74
B79: Investments sold | C79: =IFERROR('Cash Flow Data'!E17,0) -> 42 | D79: =IFERROR('Cash Flow Data'!F17,0) -> 89 | E79: =IFERROR('Cash Flow Data'!G17,0) -> 1965 | F79: =IFERROR('Cash Flow Data'!H17,0) -> 2381 | G79: =IFERROR('Cash Flow Data'!I17,0) -> 5644 | H79: =IFERROR('Cash Flow Data'!J17,0) -> 21 | I79: =IFERROR('Cash Flow Data'!K17,0) -> 226 | J79: =IFERROR('Cash Flow Data'!L17,0) -> 104 | ... L79: =IFERROR('Cash Flow Data'!N17,0) -> 10820
B80: Interest received | C80: =IFERROR('Cash Flow Data'!E18,0) -> 698 | D80: =IFERROR('Cash Flow Data'!F18,0) -> 731 | E80: =IFERROR('Cash Flow Data'!G18,0) -> 638 | F80: =IFERROR('Cash Flow Data'!H18,0) -> 690 | G80: =IFERROR('Cash Flow Data'!I18,0) -> 761 | H80: =IFERROR('Cash Flow Data'!J18,0) -> 1104 | I80: =IFERROR('Cash Flow Data'!K18,0) -> 428 | J80: =IFERROR('Cash Flow Data'!L18,0) -> 653 | ... L80: =IFERROR('Cash Flow Data'!N18,0) -> 2493
B81: Dividends received | C81: =IFERROR('Cash Flow Data'!E19,0) -> 80 | D81: =IFERROR('Cash Flow Data'!F19,0) -> 58 | E81: =IFERROR('Cash Flow Data'!G19,0) -> 620 | F81: =IFERROR('Cash Flow Data'!H19,0) -> 1797 | G81: =IFERROR('Cash Flow Data'!I19,0) -> 232 | H81: =IFERROR('Cash Flow Data'!J19,0) -> 21 | I81: =IFERROR('Cash Flow Data'!K19,0) -> 18 | J81: =IFERROR('Cash Flow Data'!L19,0) -> 32 | ... L81: =IFERROR('Cash Flow Data'!N19,0) -> 47
B82: Investment in group cos | C82: =IFERROR('Cash Flow Data'!E20,0) -> -160 | D82: =IFERROR('Cash Flow Data'!F20,0) -> 0 | E82: =IFERROR('Cash Flow Data'!G20,0) -> -107 | F82: =IFERROR('Cash Flow Data'!H20,0) -> -4 | G82: =IFERROR('Cash Flow Data'!I20,0) -> -9 | H82: =IFERROR('Cash Flow Data'!J20,0) -> -606 | I82: =IFERROR('Cash Flow Data'!K20,0) -> -10 | J82: =IFERROR('Cash Flow Data'!L20,0) -> 0 | ... L82: =IFERROR('Cash Flow Data'!N20,0) -> -150
B83: Redemp n Canc of Shares | C83: =IFERROR('Cash Flow Data'!E21,0) -> 0 | D83: =IFERROR('Cash Flow Data'!F21,0) -> 0 | E83: =IFERROR('Cash Flow Data'!G21,0) -> 0 | F83: =IFERROR('Cash Flow Data'!H21,0) -> 14 | G83: =IFERROR('Cash Flow Data'!I21,0) -> 533 | H83: =IFERROR('Cash Flow Data'!J21,0) -> 0 | I83: =IFERROR('Cash Flow Data'!K21,0) -> 0 | J83: =IFERROR('Cash Flow Data'!L21,0) -> 0 | ... L83: =IFERROR('Cash Flow Data'!N21,0) -> 108
B84: Acquisition of companies | C84: =IFERROR('Cash Flow Data'!E22,0) -> 0 | D84: =IFERROR('Cash Flow Data'!F22,0) -> -111 | E84: =IFERROR('Cash Flow Data'!G22,0) -> 0 | F84: =IFERROR('Cash Flow Data'!H22,0) -> 0 | G84: =IFERROR('Cash Flow Data'!I22,0) -> -8 | H84: =IFERROR('Cash Flow Data'!J22,0) -> -27 | I84: =IFERROR('Cash Flow Data'!K22,0) -> 0 | J84: =IFERROR('Cash Flow Data'!L22,0) -> -98 | ... L84: =IFERROR('Cash Flow Data'!N22,0) -> 0
B85: Inter corporate deposits | C85: =IFERROR('Cash Flow Data'!E23,0) -> 0 | D85: =IFERROR('Cash Flow Data'!F23,0) -> 0 | E85: =IFERROR('Cash Flow Data'!G23,0) -> 0 | F85: =IFERROR('Cash Flow Data'!H23,0) -> 0 | G85: =IFERROR('Cash Flow Data'!I23,0) -> 0 | H85: =IFERROR('Cash Flow Data'!J23,0) -> 0 | I85: =IFERROR('Cash Flow Data'!K23,0) -> 0 | J85: =IFERROR('Cash Flow Data'!L23,0) -> 0 | ... L85: =IFERROR('Cash Flow Data'!N23,0) -> -24
B86: Other investing items | C86: =IFERROR('Cash Flow Data'!E24,0) -> 456 | D86: =IFERROR('Cash Flow Data'!F24,0) -> -1289 | E86: =IFERROR('Cash Flow Data'!G24,0) -> -26663 | F86: =IFERROR('Cash Flow Data'!H24,0) -> 5360 | G86: =IFERROR('Cash Flow Data'!I24,0) -> 7335 | H86: =IFERROR('Cash Flow Data'!J24,0) -> -2659 | I86: =IFERROR('Cash Flow Data'!K24,0) -> 1051 | J86: =IFERROR('Cash Flow Data'!L24,0) -> 12813 | ... L86: =IFERROR('Cash Flow Data'!N24,0) -> -4817
B89: Cash from Financing Activity - | C89: =IFERROR('Cash Flow Data'!E25,0) -> 5201 | D89: =IFERROR('Cash Flow Data'!F25,0) -> -3795 | E89: =IFERROR('Cash Flow Data'!G25,0) -> 6205 | F89: =IFERROR('Cash Flow Data'!H25,0) -> 2012 | G89: =IFERROR('Cash Flow Data'!I25,0) -> 8830 | H89: =IFERROR('Cash Flow Data'!J25,0) -> 3390 | I89: =IFERROR('Cash Flow Data'!K25,0) -> 9904 | J89: =IFERROR('Cash Flow Data'!L25,0) -> -3380 | ... L89: =IFERROR('Cash Flow Data'!N25,0) -> -37006
B90: Proceeds from shares | C90: =IFERROR('Cash Flow Data'!E26,0) -> 0 | D90: =IFERROR('Cash Flow Data'!F26,0) -> 7433 | E90: =IFERROR('Cash Flow Data'!G26,0) -> 5 | F90: =IFERROR('Cash Flow Data'!H26,0) -> 0 | G90: =IFERROR('Cash Flow Data'!I26,0) -> 0 | H90: =IFERROR('Cash Flow Data'!J26,0) -> 3889 | I90: =IFERROR('Cash Flow Data'!K26,0) -> 2603 | J90: =IFERROR('Cash Flow Data'!L26,0) -> 19 | ... L90: =IFERROR('Cash Flow Data'!N26,0) -> 82
B91: Redemption of debentures | C91: =IFERROR('Cash Flow Data'!E27,0) -> -744 | D91: =IFERROR('Cash Flow Data'!F27,0) -> 0 | E91: =IFERROR('Cash Flow Data'!G27,0) -> 0 | F91: =IFERROR('Cash Flow Data'!H27,0) -> 0 | G91: =IFERROR('Cash Flow Data'!I27,0) -> 0 | H91: =IFERROR('Cash Flow Data'!J27,0) -> 0 | I91: =IFERROR('Cash Flow Data'!K27,0) -> 0 | J91: =IFERROR('Cash Flow Data'!L27,0) -> 0 | ... L91: =IFERROR('Cash Flow Data'!N27,0) -> 0
B92: Proceeds from borrowings | C92: =IFERROR('Cash Flow Data'!E28,0) -> 36363 | D92: =IFERROR('Cash Flow Data'!F28,0) -> 19519 | E92: =IFERROR('Cash Flow Data'!G28,0) -> 33390 | F92: =IFERROR('Cash Flow Data'!H28,0) -> 37482 | G92: =IFERROR('Cash Flow Data'!I28,0) -> 51128 | H92: =IFERROR('Cash Flow Data'!J28,0) -> 38297 | I92: =IFERROR('Cash Flow Data'!K28,0) -> 46641 | J92: =IFERROR('Cash Flow Data'!L28,0) -> 46578 | ... L92: =IFERROR('Cash Flow Data'!N28,0) -> 18747
B93: Repayment of borrowings | C93: =IFERROR('Cash Flow Data'!E29,0) -> -23332 | D93: =IFERROR('Cash Flow Data'!F29,0) -> -24924 | E93: =IFERROR('Cash Flow Data'!G29,0) -> -21732 | F93: =IFERROR('Cash Flow Data'!H29,0) -> -29964 | G93: =IFERROR('Cash Flow Data'!I29,0) -> -35198 | H93: =IFERROR('Cash Flow Data'!J29,0) -> -29847 | I93: =IFERROR('Cash Flow Data'!K29,0) -> -29709 | J93: =IFERROR('Cash Flow Data'!L29,0) -> -42816 | ... L93: =IFERROR('Cash Flow Data'!N29,0) -> -47332
B94: Interest paid fin | C94: =IFERROR('Cash Flow Data'!E30,0) -> -6307 | D94: =IFERROR('Cash Flow Data'!F30,0) -> -5716 | E94: =IFERROR('Cash Flow Data'!G30,0) -> -5336 | F94: =IFERROR('Cash Flow Data'!H30,0) -> -5411 | G94: =IFERROR('Cash Flow Data'!I30,0) -> -7005 | H94: =IFERROR('Cash Flow Data'!J30,0) -> -7518 | I94: =IFERROR('Cash Flow Data'!K30,0) -> -8123 | J94: =IFERROR('Cash Flow Data'!L30,0) -> -9251 | ... L94: =IFERROR('Cash Flow Data'!N30,0) -> -9332
B95: Dividends paid | C95: =IFERROR('Cash Flow Data'!E31,0) -> -720 | D95: =IFERROR('Cash Flow Data'!F31,0) -> -108 | E95: =IFERROR('Cash Flow Data'!G31,0) -> -121 | F95: =IFERROR('Cash Flow Data'!H31,0) -> -96 | G95: =IFERROR('Cash Flow Data'!I31,0) -> -95 | H95: =IFERROR('Cash Flow Data'!J31,0) -> -57 | I95: =IFERROR('Cash Flow Data'!K31,0) -> -30 | J95: =IFERROR('Cash Flow Data'!L31,0) -> -100 | ... L95: =IFERROR('Cash Flow Data'!N31,0) -> -1059
B96: Financial liabilities | C96: =IFERROR('Cash Flow Data'!E32,0) -> 0 | D96: =IFERROR('Cash Flow Data'!F32,0) -> 0 | E96: =IFERROR('Cash Flow Data'!G32,0) -> 0 | F96: =IFERROR('Cash Flow Data'!H32,0) -> 0 | G96: =IFERROR('Cash Flow Data'!I32,0) -> 0 | H96: =IFERROR('Cash Flow Data'!J32,0) -> -1346 | I96: =IFERROR('Cash Flow Data'!K32,0) -> -1477 | J96: =IFERROR('Cash Flow Data'!L32,0) -> -1559 | ... L96: =IFERROR('Cash Flow Data'!N32,0) -> -1924
B97: Other financing items | C97: =IFERROR('Cash Flow Data'!E33,0) -> -57 | D97: =IFERROR('Cash Flow Data'!F33,0) -> 0 | E97: =IFERROR('Cash Flow Data'!G33,0) -> 0 | F97: =IFERROR('Cash Flow Data'!H33,0) -> 0 | G97: =IFERROR('Cash Flow Data'!I33,0) -> 0 | H97: =IFERROR('Cash Flow Data'!J33,0) -> -29 | I97: =IFERROR('Cash Flow Data'!K33,0) -> 0 | J97: =IFERROR('Cash Flow Data'!L33,0) -> 3750 | ... L97: =IFERROR('Cash Flow Data'!N33,0) -> 3812
B98: Net Cash Flow | C98: =IFERROR('Cash Flow Data'!E34,0) -> 4500 | D98: =IFERROR('Cash Flow Data'!F34,0) -> -2589 | E98: =IFERROR('Cash Flow Data'!G34,0) -> -3167 | F98: =IFERROR('Cash Flow Data'!H34,0) -> 730 | G98: =IFERROR('Cash Flow Data'!I34,0) -> 6843 | H98: =IFERROR('Cash Flow Data'!J34,0) -> -3092 | I98: =IFERROR('Cash Flow Data'!K34,0) -> 13232 | J98: =IFERROR('Cash Flow Data'!L34,0) -> 6459 | ... L98: =IFERROR('Cash Flow Data'!N34,0) -> 8128

Sheet Ratio Analysis
B2: ="Ratio Analysis - "&'Data Sheet'!B1 -> Ratio Analysis - TATA MOTORS LTD
B3: Years | C3: ='Data Sheet'!B16 -> 42094 | D3: ='Data Sheet'!C16 -> 42460 | E3: ='Data Sheet'!D16 -> 42825 | F3: ='Data Sheet'!E16 -> 43190 | G3: ='Data Sheet'!F16 -> 43555 | H3: ='Data Sheet'!G16 -> 43921 | I3: ='Data Sheet'!H16 -> 44286 | J3: ='Data Sheet'!I16 -> 44651 | ... L3: ='Data Sheet'!K16 -> 45382
B5: SalesGrowth | C5: =IFERROR(HistoricalFS!C6,0) -> - | D5: =IFERROR(HistoricalFS!D6,0) -> 0.037569001 | E5: =IFERROR(HistoricalFS!E6,0) -> -0.01228033 | F5: =IFERROR(HistoricalFS!F6,0) -> 0.081047746 | G5: =IFERROR(HistoricalFS!G6,0) -> 0.035629919 | H5: =IFERROR(HistoricalFS!H6,0) -> -0.13536016 | I5: =IFERROR(HistoricalFS!I6,0) -> -0.043181168 | J5: =IFERROR(HistoricalFS!J6,0) -> 0.11472967 | ... L5: =IFERROR(HistoricalFS!L6,0) -> 0.26580803
B6: EBITDA Growth | C6: - | D6: =IFERROR(HistoricalFS!D17/HistoricalFS!C17-1,0) -> -0.0073531746 | E6: =IFERROR(HistoricalFS!E17/HistoricalFS!D17-1,0) -> -0.37749388 | F6: =IFERROR(HistoricalFS!F17/HistoricalFS!E17-1,0) -> 0.32549483 | G6: =IFERROR(HistoricalFS!G17/HistoricalFS!F17-1,0) -> -0.09158073 | H6: =IFERROR(HistoricalFS!H17/HistoricalFS!G17-1,0) -> -0.24326091 | I6: =IFERROR(HistoricalFS!I17/HistoricalFS!H17-1,0) -> 0.82862373 | J6: =IFERROR(HistoricalFS!J17/HistoricalFS!I17-1,0) -> -0.28835682 | K6: =IFERROR(HistoricalFS!K17/HistoricalFS!J17-1,0) -> 0.027502244 | L6: =IFERROR(HistoricalFS!L17/HistoricalFS!K17-1,0) -> 1.1444264
B7: EBIT Growth | C7: - | D7: =IFERROR(HistoricalFS!D26/HistoricalFS!C26-1,0) -> -0.2046519 | E7: =IFERROR(HistoricalFS!E26/HistoricalFS!D26-1,0) -> -0.99674105 | F7: =IFERROR(HistoricalFS!F26/HistoricalFS!E26-1,0) -> 68.384313 | G7: =IFERROR(HistoricalFS!G26/HistoricalFS!F26-1,0) -> -1.8286688 | H7: =IFERROR(HistoricalFS!H26/HistoricalFS!G26-1,0) -> 2.2111399 | I7: =IFERROR(HistoricalFS!I26/HistoricalFS!H26-1,0) -> -1.6304609 | J7: =IFERROR(HistoricalFS!J26/HistoricalFS!I26-1,0) -> -2.4709828 | K7: =IFERROR(HistoricalFS!K26/HistoricalFS!J26-1,0) -> 0.027394516 | L7: =IFERROR(HistoricalFS!L26/HistoricalFS!K26-1,0) -> -3.5729999
B8: Net Profit Growth | C8: - | D8: =IFERROR(HistoricalFS!D32/HistoricalFS!C32-1,0) -> 0.10025491 | E8: =IFERROR(HistoricalFS!E32/HistoricalFS!D32-1,0) -> -1.2908937 | F8: =IFERROR(HistoricalFS!F32/HistoricalFS!E32-1,0) -> -0.63618014 | G8: =IFERROR(HistoricalFS!G32/HistoricalFS!F32-1,0) -> -0.8335034 | H8: =IFERROR(HistoricalFS!H32/HistoricalFS!G32-1,0) -> 44.556729 | I8: =IFERROR(HistoricalFS!I32/HistoricalFS!H32-1,0) -> -1.3149366 | J8: =IFERROR(HistoricalFS!J32/HistoricalFS!I32-1,0) -> -5.3319849 | K8: =IFERROR(HistoricalFS!K32/HistoricalFS!J32-1,0) -> -0.27448365 | L8: =IFERROR(HistoricalFS!L32/HistoricalFS!K32-1,0) -> -3.8060011
B9: Dividend Growth | C9: -
B11: Gross Margin
B12: Operating Margin
B13: EBITDA Margin
B14: EBIT Margin
B15: EBT Margin
B16: Net Profit Margin
B18: SalesExpenses%sales
B19: Depreciation % Sales
B20: OperatingIncome%Sales
B22: Return On Capital Employed
B23: Retained Earningns%
B24: Return On equity%
... B41: CFO/Total Debt

Sheet Forecasting
B1: ='Data Sheet'!B1&" - " &'Data Sheet'!A17 -> TATA MOTORS LTD - Sales
B2: Year Weight | C2: Year | D2: Sales | E2: Sales Growth
B3: 1 | C3: 2015 | D3: 263159 | E3: -
B4: =B3+1 -> 2 | C4: =C3+1 -> 2016 | D4: 273046 | E4: =D4/D3-1 -> 0.037570442
B5: =B4+1 -> 3 | C5: =C4+1 -> 2017 | D5: 269693 | E5: =D5/D4-1 -> -0.012279982
B6: =B5+1 -> 4 | C6: =C5+1 -> 2018 | D6: 291550 | E6: =D6/D5-1 -> 0.081044002
B7: =B6+1 -> 5 | C7: =C6+1 -> 2019 | D7: 301938 | E7: =D7/D6-1 -> 0.035630252
B8: =B7+1 -> 6 | C8: =C7+1 -> 2020 | D8: 261068 | E8: =D8/D7-1 -> -0.13535891
B9: =B8+1 -> 7 | C9: =C8+1 -> 2021 | D9: 249795 | E9: =D9/D8-1 -> -0.043180321
B10: =B9+1 -> 8 | C10: =C9+1 -> 2022 | D10: 278454 | E10: =D10/D9-1 -> 0.11473008
B11: =B10+1 -> 9 | C11: =C10+1 -> 2023 | D11: 345967 | E11: =D11/D10-1 -> 0.24245656
B12: =B11+1 -> 10 | C12: =C11+1 -> 2024 | D12: 437928 | E12: =D12/D11-1 -> 0.26580859
B13: =B12+1 -> 11 | C13: =C12+1 -> 2025 | D13: =$G$37+(B13*$G$38) -> 362627.73 | E13: =D13/D12-1 -> -0.17194668
B14: =B13+1 -> 12 | C14: =C13+1 -> 2026 | D14: =$G$37+(B14*$G$38) -> 374512.81 | E14: =D14/D13-1 -> 0.032774875
B15: =B14+1 -> 13 | C15: =C14+1 -> 2027 | D15: =$G$37+(B15*$G$38) -> 386397.89 | E15: =D15/D14-1 -> 0.031734772
B16: =B15+1 -> 14 | C16: =C15+1 -> 2028 | D16: =$G$37+(B16*$G$38) -> 398282.97 | E16: =D16/D15-1 -> 0.030758653
B17: =B16+1 -> 15 | C17: =C16+1 -> 2029 | D17: =$G$37+(B17*$G$38) -> 410168.05 | E17: =D17/D16-1 -> 0.029840791
B21: Arthematic Growth | D21: =AVERAGE(E4:E12) -> 0.065157857 | F21: SUMMARY OUTPUT
B22: Geometric Growth | D22: =_xlfn.RRI(B12,D3,D12) -> 0.052248823
F23: Regression Statistics
B24: Standard Deviation | D24: =_xlfn.STDEV.S(E4:E12) -> 0.12941166 | F24: Multiple R | G24: 0.63788594
F25: R Square | G25: 0.40689848
F26: Adjusted R Square | G26: 0.33276079
F27: Standard Error | G27: 46079.264
F28: Observations | G28: 10
F30: ANOVA
G31: df | H31: SS | I31: MS | J31: F | K31: Significance F
F32: Regression | G32: 1 | H32: 1.1653546e+10 | I32: 1.1653546e+10 | J32: 5.4884159 | K32: 0.047213544
F33: Residual | G33: 8 | H33: 1.6986388e+10 | I33: 2.1232986e+09
F34: Total | G34: 9 | H34: 2.8639934e+10
G36: Coefficients | H36: Standard Error | I36: t Stat | J36: P-value | K36: Lower 95% | L36: Upper 95% | M36: Lower 95.0% | N36: Upper 95.0%
F37: Intercept | G37: 231891.87 | H37: 31478.13 | I37: 7.3667612 | J37: 7.8661724e-05 | K37: 159303.17 | L37: 304480.56 | M37: 159303.17 | N37: 304480.56
F38: Year Weight | G38: 11885.079 | H38: 5073.16 | I38: 2.3427368 | J38: 0.047213544 | K38: 186.35088 | L38: 23583.807 | M38: 186.35088 | N38: 23583.807

Sheet WACC
B2: Weighted Average Cost of Capital
C13: Weighted Average Cost of Capital
C15: All figures are in INR unless stated otherwise.
C17: Peer Comps
H18: Debt/ | I18: Debt/ | J18: Levered | K18: Unlevered
C19: Name | D19: Country | E19: Total Debt | F19: Total Equity | G19: Tax Rate 1 | H19: Equity | I19: Capital | J19: Beta 2 | K19: Beta 3
C21: Hind. Unilever | D21: India | E21: 1139 | F21: 611503.9 | G21: 0.3 | H21: 0.0019 | I21: 0.0019 | J21: 1 | K21: 1
C22: Nestle India | D22: India | E22: 279.9 | F22: 182975 | G22: 0.3 | H22: 0.0015 | I22: 0.0015 | J22: 1 | K22: 1
C23: Britannia Inds. | D23: India | E23: 3037.7 | F23: 110690 | G23: 0.3 | H23: 0.0274 | I23: 0.0267 | J23: 1 | K23: 0.98
C24: Godrej Consumer | D24: India | E24: 1164.5 | F24: 96256.4 | G24: 0.3 | H24: 0.0121 | I24: 0.012 | J24: 1 | K24: 0.99
C25: Dabur India | D25: India | E25: 1068.1 | F25: 94940.4 | G25: 0.3 | H25: 0.0113 | I25: 0.0111 | J25: 1 | K25: 0.99
F27: Average | G27: 0.3 | H27: 0.0108 | I27: 0.0106 | J27: 1 | K27: 0.99
F28: Median | G28: 0.3 | H28: 0.0113 | I28: 0.0111 | J28: 1 | K28: 0.99
C31: Cost of Debt | H31: Cost of Equity
C33: Pre-tax Cost of Debt | F33: 0.084 | H33: Risk Free Rate | K33: 0.065
C34: Tax Rate | F34: 0.3 | H34: Equity Risk Premium | K34: 0.08
C35: After Tax Cost of Debt | F35: 0.0588 | H35: Levered Beta 4 | K35: 1.51
H36: Cost of Equity | K36: 0.1854
C39: Capital Structure | H39: Levered Beta
E41: Current | F41: Target | H41: Comps Median Unlevered Beta | K41: 0.99
C42: Total Debt | D42: 17440 | E42: 0.3509 | F42: 0.425 | H42: Target Debt/ Equity | K42: 0.7391
C43: Market Capitalization | D43: 32265 | E43: 0.6491 | F43: 0.575 | H43: Tax Rate | K43: 0.3
C44: Total Capitalization | D44: 49705 | E44: 1 | F44: 1 | H44: Levered Beta | K44: 1.51
C46: Debt / Equity | E46: 0.5405 | F46: 0.7391 | H46: Weighted Average Cost of Capital
C48: 1. Tax Rate considered as Marginal Tax Rate for the country | J48: Total Cost | K48: Total Weight
C49: 2. Levered Beta is based on 5 year monthly data | H49: Debt Capital | J49: 0.0588 | K49: 0.425
C50: 3. Unlevered Beta = Levered Beta/(1+(1-Tax Rate) x Debt/Equity) | H50: Equity Capital | J50: 0.1854 | K50: 0.575
C51: 4. Levered Beta = Unlevered Beta*(1+(1-Tax Rate) x Debt/Equity) | H51: Weighted Average Cost of Capital | K51: 0.1316

Sheet Cash Flow Data
E3: 42064 | F3: 42430 | G3: 42795 | H3: 43160 | I3: 43525 | J3: 43891 | K3: 44256 | L3: 44621 | M3: 44986 | N3: 45352
B4: Cash from Operating Activity - | E4: 35531 | F4: 37900 | G4: 30199 | H4: 23857 | I4: 18891 | J4: 26633 | K4: 29001 | L4: 14283 | M4: 35388 | N4: 67915
B5: Profit from operations | E5: 43397 | F5: 38626 | G5: 28840 | H5: 33312 | I5: 28771 | J5: 23352 | K5: 31198 | L5: 26943 | M5: 41694 | N5: 65106
B6: Receivables | E6: -3179 | F6: -2223 | G6: -4152 | H6: -10688 | I6: -9109 | J6: 9950 | K6: -5505 | L6: 185 | M6: -2213 | N6: -1875
B7: Inventory | E7: -3692 | F7: -5743 | G7: -6621 | H7: -3560 | I7: 2069 | J7: 2326 | K7: 3814 | L7: 472 | M7: -5665 | N7: -7265
B8: Payables | E8: 3598 | F8: 3947 | G8: 9301 | H8: 7320 | I8: -4692 | J8: -8085 | K8: 5748 | L8: -7012 | M8: 6945 | N8: 13706
B9: Loans Advances | E9: 0 | F9: -520 | G9: 0 | H9: 0 | I9: 0 | J9: 0 | K9: 0 | L9: 0 | M9: 0 | N9: 0
B10: Other WC items | E10: -398 | F10: 5852 | G10: 4727 | H10: 494 | I10: 4512 | J10: 875 | K10: -4150 | L10: -4396 | M10: -2194 | N10: 2760
B11: Working capital changes | E11: -3672 | F11: 1313 | G11: 3254 | H11: -6434 | I11: -7221 | J11: 5065 | K11: -93 | L11: -10750 | M11: -3127 | N11: 7325
B12: Direct taxes | E12: -4194 | F12: -2040 | G12: -1895 | H12: -3021 | I12: -2659 | J12: -1785 | K12: -2105 | L12: -1910 | M12: -3179 | N12: -4516
B13: Cash from Investing Activity - | E13: -36232 | F13: -36694 | G13: -39571 | H13: -25139 | I13: -20878 | J13: -33115 | K13: -25672 | L13: -4444 | M13: -15417 | N13: -22782
B14: Fixed assets purchased | E14: -31962 | F14: -31503 | G14: -16072 | H14: -35079 | I14: -35304 | J14: -29702 | K14: -20205 | L14: -15168 | M14: -19230 | N14: -31414
B15: Fixed assets sold | E15: 74 | F15: 59 | G15: 53 | H15: 30 | I15: 67 | J15: 171 | K15: 351 | L15: 230 | M15: 285 | N15: 231
... B34: Net Cash Flow | E34: 4500 | F34: -2589 | G34: -3167 | H34: 730 | I34: 6843 | J34: -3092 | K34: 13232 | L34: 6459 | M34: -6272 | N34: 8128

Sheet Data
